[
  {
    "id": 5003,
    "name": "Mana Break",
    "img": "https://hgv-hyperstone.azurewebsites.net/abilities/antimage_mana_break.png",
    "is_ultimate": false,
    "has_upgrade": false,
    "picks": 0.6873823,
    "wins": 0.7265152,
    "win_rate": 0.525479436
  },
  {
    "id": 5421,
    "name": "Disruption",
    "img": "https://hgv-hyperstone.azurewebsites.net/abilities/shadow_demon_disruption.png",
    "is_ultimate": false,
    "has_upgrade": false,
    "picks": 0.190207154,
    "wins": 0.1969697,
    "win_rate": 0.5148515
  },
  {
    "id": 5595,
    "name": "Overwhelming Odds",
    "img": "https://hgv-hyperstone.azurewebsites.net/abilities/legion_commander_overwhelming_odds.png",
    "is_ultimate": false,
    "has_upgrade": false,
    "picks": 0.316007525,
    "wins": 0.289393932,
    "win_rate": 0.455303937
  },
  {
    "id": 5289,
    "name": "The Swarm",
    "img": "https://hgv-hyperstone.azurewebsites.net/abilities/weaver_the_swarm.png",
    "is_ultimate": false,
    "has_upgrade": false,
    "picks": 0.317890763,
    "wins": 0.3,
    "win_rate": 0.469194323
  },
  {
    "id": 5290,
    "name": "Shukuchi",
    "img": "https://hgv-hyperstone.azurewebsites.net/abilities/weaver_shukuchi.png",
    "is_ultimate": false,
    "has_upgrade": false,
    "picks": 0.126930326,
    "wins": 0.154545456,
    "win_rate": 0.605341256
  },
  {
    "id": 5596,
    "name": "Press The Attack",
    "img": "https://hgv-hyperstone.azurewebsites.net/abilities/legion_commander_press_the_attack.png",
    "is_ultimate": false,
    "has_upgrade": false,
    "picks": 0.36572504,
    "wins": 0.363636374,
    "win_rate": 0.494335741
  },
  {
    "id": 5072,
    "name": "Phase Shift",
    "img": "https://hgv-hyperstone.azurewebsites.net/abilities/puck_phase_shift.png",
    "is_ultimate": false,
    "has_upgrade": false,
    "picks": 0.146139354,
    "wins": 0.151515156,
    "win_rate": 0.5154639
  },
  {
    "id": 5587,
    "name": "Curse of Avernus",
    "img": "https://hgv-hyperstone.azurewebsites.net/abilities/abaddon_frostmourne.png",
    "is_ultimate": false,
    "has_upgrade": false,
    "picks": 0.398116767,
    "wins": 0.418939382,
    "win_rate": 0.5231788
  },
  {
    "id": 5585,
    "name": "Mist Coil",
    "img": "https://hgv-hyperstone.azurewebsites.net/abilities/abaddon_death_coil.png",
    "is_ultimate": false,
    "has_upgrade": false,
    "picks": 0.0463276841,
    "wins": 0.0424242429,
    "win_rate": 0.455284566
  },
  {
    "id": 5619,
    "name": "Reflection",
    "img": "https://hgv-hyperstone.azurewebsites.net/abilities/terrorblade_reflection.png",
    "is_ultimate": false,
    "has_upgrade": false,
    "picks": 0.166854993,
    "wins": 0.182575762,
    "win_rate": 0.54401803
  },
  {
    "id": 5281,
    "name": "Incapacitating Bite",
    "img": "https://hgv-hyperstone.azurewebsites.net/abilities/broodmother_incapacitating_bite.png",
    "is_ultimate": false,
    "has_upgrade": false,
    "picks": 0.535969853,
    "wins": 0.564393938,
    "win_rate": 0.5235418
  },
  {
    "id": 5467,
    "name": "Mirror Image",
    "img": "https://hgv-hyperstone.azurewebsites.net/abilities/naga_siren_mirror_image.png",
    "is_ultimate": false,
    "has_upgrade": false,
    "picks": 1.0,
    "wins": 1.0,
    "win_rate": 0.497175127
  },
  {
    "id": 5469,
    "name": "Rip Tide",
    "img": "https://hgv-hyperstone.azurewebsites.net/abilities/naga_siren_rip_tide.png",
    "is_ultimate": false,
    "has_upgrade": false,
    "picks": 0.5322034,
    "wins": 0.49848485,
    "win_rate": 0.465675861
  },
  {
    "id": 5031,
    "name": "Torrent",
    "img": "https://hgv-hyperstone.azurewebsites.net/abilities/kunkka_torrent.png",
    "is_ultimate": false,
    "has_upgrade": false,
    "picks": 0.1566855,
    "wins": 0.149242431,
    "win_rate": 0.473557681
  },
  {
    "id": 5593,
    "name": "Natural Order",
    "img": "https://hgv-hyperstone.azurewebsites.net/abilities/elder_titan_natural_order.png",
    "is_ultimate": false,
    "has_upgrade": false,
    "picks": 0.166854993,
    "wins": 0.154545456,
    "win_rate": 0.4604966
  },
  {
    "id": 5015,
    "name": "Bloodrage",
    "img": "https://hgv-hyperstone.azurewebsites.net/abilities/bloodseeker_bloodrage.png",
    "is_ultimate": false,
    "has_upgrade": false,
    "picks": 0.215442568,
    "wins": 0.192424238,
    "win_rate": 0.444055945
  },
  {
    "id": 5143,
    "name": "Blink Strike",
    "img": "https://hgv-hyperstone.azurewebsites.net/abilities/riki_blink_strike.png",
    "is_ultimate": false,
    "has_upgrade": false,
    "picks": 0.300188333,
    "wins": 0.277272731,
    "win_rate": 0.459222078
  },
  {
    "id": 5482,
    "name": "Gravekeeper's Cloak",
    "img": "https://hgv-hyperstone.azurewebsites.net/abilities/visage_gravekeepers_cloak.png",
    "is_ultimate": false,
    "has_upgrade": false,
    "picks": 0.290395468,
    "wins": 0.3007576,
    "win_rate": 0.5149157
  },
  {
    "id": 5516,
    "name": "Return",
    "img": "https://hgv-hyperstone.azurewebsites.net/abilities/centaur_return.png",
    "is_ultimate": false,
    "has_upgrade": false,
    "picks": 0.188323915,
    "wins": 0.193939388,
    "win_rate": 0.512
  },
  {
    "id": 5271,
    "name": "Inner Vitality",
    "img": "https://hgv-hyperstone.azurewebsites.net/abilities/huskar_inner_vitality.png",
    "is_ultimate": false,
    "has_upgrade": false,
    "picks": 0.247457623,
    "wins": 0.25757575,
    "win_rate": 0.5175038
  },
  {
    "id": 5273,
    "name": "Berserker's Blood",
    "img": "https://hgv-hyperstone.azurewebsites.net/abilities/huskar_berserkers_blood.png",
    "is_ultimate": false,
    "has_upgrade": false,
    "picks": 0.265536726,
    "wins": 0.302272737,
    "win_rate": 0.5659574
  },
  {
    "id": 5400,
    "name": "Thunder Clap",
    "img": "https://hgv-hyperstone.azurewebsites.net/abilities/brewmaster_thunder_clap.png",
    "is_ultimate": false,
    "has_upgrade": false,
    "picks": 0.280226,
    "wins": 0.2530303,
    "win_rate": 0.44892472
  },
  {
    "id": 5279,
    "name": "Spawn Spiderlings",
    "img": "https://hgv-hyperstone.azurewebsites.net/abilities/broodmother_spawn_spiderlings.png",
    "is_ultimate": false,
    "has_upgrade": false,
    "picks": 0.117514126,
    "wins": 0.0969696939,
    "win_rate": 0.410256416
  },
  {
    "id": 5280,
    "name": "Spin Web",
    "img": "https://hgv-hyperstone.azurewebsites.net/abilities/broodmother_spin_web.png",
    "is_ultimate": false,
    "has_upgrade": false,
    "picks": 0.1992467,
    "wins": 0.229545459,
    "win_rate": 0.5727788
  },
  {
    "id": 5173,
    "name": "Shadow Strike",
    "img": "https://hgv-hyperstone.azurewebsites.net/abilities/queenofpain_shadow_strike.png",
    "is_ultimate": false,
    "has_upgrade": false,
    "picks": 0.2967985,
    "wins": 0.285606056,
    "win_rate": 0.4784264
  },
  {
    "id": 5378,
    "name": "Glaives of Wisdom",
    "img": "https://hgv-hyperstone.azurewebsites.net/abilities/silencer_glaives_of_wisdom.png",
    "is_ultimate": false,
    "has_upgrade": true,
    "picks": 0.246327683,
    "wins": 0.246212125,
    "win_rate": 0.4969419
  },
  {
    "id": 5583,
    "name": "Ancient Seal",
    "img": "https://hgv-hyperstone.azurewebsites.net/abilities/skywrath_mage_ancient_seal.png",
    "is_ultimate": false,
    "has_upgrade": false,
    "picks": 0.11186441,
    "wins": 0.09242424,
    "win_rate": 0.4107744
  },
  {
    "id": 5613,
    "name": "Firestorm",
    "img": "https://hgv-hyperstone.azurewebsites.net/abilities/abyssal_underlord_firestorm.png",
    "is_ultimate": false,
    "has_upgrade": false,
    "picks": 0.126177028,
    "wins": 0.134090915,
    "win_rate": 0.5283582
  },
  {
    "id": 5615,
    "name": "Atrophy Aura",
    "img": "https://hgv-hyperstone.azurewebsites.net/abilities/abyssal_underlord_atrophy_aura.png",
    "is_ultimate": false,
    "has_upgrade": true,
    "picks": 0.244821087,
    "wins": 0.261363626,
    "win_rate": 0.5307692
  },
  {
    "id": 5130,
    "name": "Shackleshot",
    "img": "https://hgv-hyperstone.azurewebsites.net/abilities/windrunner_shackleshot.png",
    "is_ultimate": false,
    "has_upgrade": false,
    "picks": 0.33709982,
    "wins": 0.335606068,
    "win_rate": 0.49497208
  },
  {
    "id": 5427,
    "name": "Reality Rift",
    "img": "https://hgv-hyperstone.azurewebsites.net/abilities/chaos_knight_reality_rift.png",
    "is_ultimate": false,
    "has_upgrade": false,
    "picks": 0.665913343,
    "wins": 0.6159091,
    "win_rate": 0.459841639
  },
  {
    "id": 5178,
    "name": "Venomous Gale",
    "img": "https://hgv-hyperstone.azurewebsites.net/abilities/venomancer_venomous_gale.png",
    "is_ultimate": false,
    "has_upgrade": false,
    "picks": 0.2828625,
    "wins": 0.275757581,
    "win_rate": 0.4846871
  },
  {
    "id": 5495,
    "name": "Pounce",
    "img": "https://hgv-hyperstone.azurewebsites.net/abilities/slark_pounce.png",
    "is_ultimate": false,
    "has_upgrade": false,
    "picks": 0.396610171,
    "wins": 0.369696975,
    "win_rate": 0.4634378
  },
  {
    "id": 5094,
    "name": "Storm Hammer",
    "img": "https://hgv-hyperstone.azurewebsites.net/abilities/sven_storm_bolt.png",
    "is_ultimate": false,
    "has_upgrade": false,
    "picks": 0.102071561,
    "wins": 0.0969696939,
    "win_rate": 0.472324729
  },
  {
    "id": 5154,
    "name": "Shrapnel",
    "img": "https://hgv-hyperstone.azurewebsites.net/abilities/sniper_shrapnel.png",
    "is_ultimate": false,
    "has_upgrade": false,
    "picks": 0.333333343,
    "wins": 0.399242431,
    "win_rate": 0.5954802
  },
  {
    "id": 5505,
    "name": "Mystic Snake",
    "img": "https://hgv-hyperstone.azurewebsites.net/abilities/medusa_mystic_snake.png",
    "is_ultimate": false,
    "has_upgrade": true,
    "picks": 0.198870063,
    "wins": 0.198484853,
    "win_rate": 0.496212125
  },
  {
    "id": 5287,
    "name": "Shadow Walk",
    "img": "https://hgv-hyperstone.azurewebsites.net/abilities/bounty_hunter_wind_walk.png",
    "is_ultimate": false,
    "has_upgrade": false,
    "picks": 0.13333334,
    "wins": 0.125757575,
    "win_rate": 0.468926549
  },
  {
    "id": 5391,
    "name": "Arcane Orb",
    "img": "https://hgv-hyperstone.azurewebsites.net/abilities/obsidian_destroyer_arcane_orb.png",
    "is_ultimate": false,
    "has_upgrade": false,
    "picks": 0.117890775,
    "wins": 0.106060609,
    "win_rate": 0.447284341
  },
  {
    "id": 5393,
    "name": "Essence Aura",
    "img": "https://hgv-hyperstone.azurewebsites.net/abilities/obsidian_destroyer_essence_aura.png",
    "is_ultimate": false,
    "has_upgrade": false,
    "picks": 0.06591337,
    "wins": 0.0583333336,
    "win_rate": 0.44
  },
  {
    "id": 5119,
    "name": "Kraken Shell",
    "img": "https://hgv-hyperstone.azurewebsites.net/abilities/tidehunter_kraken_shell.png",
    "is_ultimate": false,
    "has_upgrade": false,
    "picks": 0.222598866,
    "wins": 0.235606059,
    "win_rate": 0.526226759
  },
  {
    "id": 5678,
    "name": "Magnetic Field",
    "img": "https://hgv-hyperstone.azurewebsites.net/abilities/arc_warden_magnetic_field.png",
    "is_ultimate": false,
    "has_upgrade": false,
    "picks": 0.2708098,
    "wins": 0.256818175,
    "win_rate": 0.471488178
  },
  {
    "id": 5363,
    "name": "Flak Cannon",
    "img": "https://hgv-hyperstone.azurewebsites.net/abilities/gyrocopter_flak_cannon.png",
    "is_ultimate": false,
    "has_upgrade": false,
    "picks": 0.372881353,
    "wins": 0.3780303,
    "win_rate": 0.5040404
  },
  {
    "id": 6339,
    "name": "Bramble Maze",
    "img": "https://hgv-hyperstone.azurewebsites.net/abilities/dark_willow_bramble_maze.png",
    "is_ultimate": false,
    "has_upgrade": false,
    "picks": 0.174764588,
    "wins": 0.161363631,
    "win_rate": 0.459051728
  },
  {
    "id": 5160,
    "name": "Ghost Shroud",
    "img": "https://hgv-hyperstone.azurewebsites.net/abilities/necrolyte_sadist.png",
    "is_ultimate": false,
    "has_upgrade": false,
    "picks": 0.09303202,
    "wins": 0.0780303,
    "win_rate": 0.417004049
  },
  {
    "id": 5275,
    "name": "Void",
    "img": "https://hgv-hyperstone.azurewebsites.net/abilities/night_stalker_void.png",
    "is_ultimate": false,
    "has_upgrade": false,
    "picks": 0.3077213,
    "wins": 0.287878782,
    "win_rate": 0.4651163
  },
  {
    "id": 5087,
    "name": "Vampiric Aura",
    "img": "https://hgv-hyperstone.azurewebsites.net/abilities/skeleton_king_vampiric_aura.png",
    "is_ultimate": false,
    "has_upgrade": false,
    "picks": 0.55291903,
    "wins": 0.5113636,
    "win_rate": 0.459809273
  },
  {
    "id": 5027,
    "name": "Blade Dance",
    "img": "https://hgv-hyperstone.azurewebsites.net/abilities/juggernaut_blade_dance.png",
    "is_ultimate": false,
    "has_upgrade": false,
    "picks": 0.393220335,
    "wins": 0.37348485,
    "win_rate": 0.4722222
  },
  {
    "id": 5366,
    "name": "Unstable Concoction",
    "img": "https://hgv-hyperstone.azurewebsites.net/abilities/alchemist_unstable_concoction.png",
    "is_ultimate": false,
    "has_upgrade": false,
    "picks": 0.178907722,
    "wins": 0.156818181,
    "win_rate": 0.435789466
  },
  {
    "id": 6346,
    "name": "Heartpiercer",
    "img": "https://hgv-hyperstone.azurewebsites.net/abilities/pangolier_heartpiercer.png",
    "is_ultimate": false,
    "has_upgrade": false,
    "picks": 0.716007531,
    "wins": 0.707575738,
    "win_rate": 0.491320372
  },
  {
    "id": 5614,
    "name": "Pit of Malice",
    "img": "https://hgv-hyperstone.azurewebsites.net/abilities/abyssal_underlord_pit_of_malice.png",
    "is_ultimate": false,
    "has_upgrade": false,
    "picks": 0.261770248,
    "wins": 0.250757575,
    "win_rate": 0.476259
  },
  {
    "id": 5460,
    "name": "Kinetic Field",
    "img": "https://hgv-hyperstone.azurewebsites.net/abilities/disruptor_kinetic_field.png",
    "is_ultimate": false,
    "has_upgrade": false,
    "picks": 0.157062143,
    "wins": 0.146969691,
    "win_rate": 0.4652278
  },
  {
    "id": 5586,
    "name": "Aphotic Shield",
    "img": "https://hgv-hyperstone.azurewebsites.net/abilities/abaddon_aphotic_shield.png",
    "is_ultimate": false,
    "has_upgrade": false,
    "picks": 0.221468925,
    "wins": 0.2159091,
    "win_rate": 0.484693885
  },
  {
    "id": 5196,
    "name": "Psi Blades",
    "img": "https://hgv-hyperstone.azurewebsites.net/abilities/templar_assassin_psi_blades.png",
    "is_ultimate": false,
    "has_upgrade": false,
    "picks": 0.300941616,
    "wins": 0.326515138,
    "win_rate": 0.5394243
  },
  {
    "id": 5368,
    "name": "Greevil's Greed",
    "img": "https://hgv-hyperstone.azurewebsites.net/abilities/alchemist_goblins_greed.png",
    "is_ultimate": false,
    "has_upgrade": false,
    "picks": 0.2542373,
    "wins": 0.2621212,
    "win_rate": 0.5125926
  },
  {
    "id": 5159,
    "name": "Heartstopper Aura",
    "img": "https://hgv-hyperstone.azurewebsites.net/abilities/necrolyte_heartstopper_aura.png",
    "is_ultimate": false,
    "has_upgrade": false,
    "picks": 0.2613936,
    "wins": 0.2962121,
    "win_rate": 0.563400567
  },
  {
    "id": 5397,
    "name": "Feral Impulse",
    "img": "https://hgv-hyperstone.azurewebsites.net/abilities/lycan_feral_impulse.png",
    "is_ultimate": false,
    "has_upgrade": false,
    "picks": 0.256497175,
    "wins": 0.279545456,
    "win_rate": 0.5418502
  },
  {
    "id": 5132,
    "name": "Windrun",
    "img": "https://hgv-hyperstone.azurewebsites.net/abilities/windrunner_windrun.png",
    "is_ultimate": false,
    "has_upgrade": false,
    "picks": 0.23013182,
    "wins": 0.235606059,
    "win_rate": 0.5090016
  },
  {
    "id": 5140,
    "name": "Maledict",
    "img": "https://hgv-hyperstone.azurewebsites.net/abilities/witch_doctor_maledict.png",
    "is_ultimate": false,
    "has_upgrade": false,
    "picks": 0.125800371,
    "wins": 0.11212121,
    "win_rate": 0.443113774
  },
  {
    "id": 5237,
    "name": "Battery Assault",
    "img": "https://hgv-hyperstone.azurewebsites.net/abilities/rattletrap_battery_assault.png",
    "is_ultimate": false,
    "has_upgrade": false,
    "picks": 0.186440676,
    "wins": 0.1659091,
    "win_rate": 0.442424238
  },
  {
    "id": 5104,
    "name": "Caustic Finale",
    "img": "https://hgv-hyperstone.azurewebsites.net/abilities/sandking_caustic_finale.png",
    "is_ultimate": false,
    "has_upgrade": false,
    "picks": 0.331826746,
    "wins": 0.3469697,
    "win_rate": 0.5198638
  },
  {
    "id": 5589,
    "name": "Echo Stomp",
    "img": "https://hgv-hyperstone.azurewebsites.net/abilities/elder_titan_echo_stomp.png",
    "is_ultimate": false,
    "has_upgrade": false,
    "picks": 0.0433145,
    "wins": 0.03560606,
    "win_rate": 0.408695638
  },
  {
    "id": 5084,
    "name": "Unstable Current",
    "img": "https://hgv-hyperstone.azurewebsites.net/abilities/razor_unstable_current.png",
    "is_ultimate": false,
    "has_upgrade": false,
    "picks": 0.287758946,
    "wins": 0.338636369,
    "win_rate": 0.585078537
  },
  {
    "id": 5347,
    "name": "Chilling Touch",
    "img": "https://hgv-hyperstone.azurewebsites.net/abilities/ancient_apparition_chilling_touch.png",
    "is_ultimate": false,
    "has_upgrade": false,
    "picks": 0.144632772,
    "wins": 0.12954545,
    "win_rate": 0.4453125
  },
  {
    "id": 5192,
    "name": "Blur",
    "img": "https://hgv-hyperstone.azurewebsites.net/abilities/phantom_assassin_blur.png",
    "is_ultimate": false,
    "has_upgrade": false,
    "picks": 0.465160072,
    "wins": 0.4537879,
    "win_rate": 0.48502025
  },
  {
    "id": 5269,
    "name": "Nature's Attendants",
    "img": "https://hgv-hyperstone.azurewebsites.net/abilities/enchantress_natures_attendants.png",
    "is_ultimate": false,
    "has_upgrade": false,
    "picks": 0.222598866,
    "wins": 0.2219697,
    "win_rate": 0.4957699
  },
  {
    "id": 5194,
    "name": "Refraction",
    "img": "https://hgv-hyperstone.azurewebsites.net/abilities/templar_assassin_refraction.png",
    "is_ultimate": false,
    "has_upgrade": false,
    "picks": 0.177024484,
    "wins": 0.179545447,
    "win_rate": 0.5042553
  },
  {
    "id": 5435,
    "name": "Leech Seed",
    "img": "https://hgv-hyperstone.azurewebsites.net/abilities/treant_leech_seed.png",
    "is_ultimate": false,
    "has_upgrade": false,
    "picks": 0.169114873,
    "wins": 0.157575756,
    "win_rate": 0.46325168
  },
  {
    "id": 5007,
    "name": "Berserker's Call",
    "img": "https://hgv-hyperstone.azurewebsites.net/abilities/axe_berserkers_call.png",
    "is_ultimate": false,
    "has_upgrade": false,
    "picks": 0.180037662,
    "wins": 0.184090912,
    "win_rate": 0.5083682
  },
  {
    "id": 5009,
    "name": "Counter Helix",
    "img": "https://hgv-hyperstone.azurewebsites.net/abilities/axe_counter_helix.png",
    "is_ultimate": false,
    "has_upgrade": false,
    "picks": 0.2542373,
    "wins": 0.261363626,
    "win_rate": 0.51111114
  },
  {
    "id": 5691,
    "name": "Time Dilation",
    "img": "https://hgv-hyperstone.azurewebsites.net/abilities/faceless_void_time_dilation.png",
    "is_ultimate": false,
    "has_upgrade": false,
    "picks": 0.162335217,
    "wins": 0.159848481,
    "win_rate": 0.489559174
  },
  {
    "id": 5128,
    "name": "Arcane Aura",
    "img": "https://hgv-hyperstone.azurewebsites.net/abilities/crystal_maiden_brilliance_aura.png",
    "is_ultimate": false,
    "has_upgrade": false,
    "picks": 0.124670431,
    "wins": 0.128787875,
    "win_rate": 0.513595164
  },
  {
    "id": 5088,
    "name": "Mortal Strike",
    "img": "https://hgv-hyperstone.azurewebsites.net/abilities/skeleton_king_mortal_strike.png",
    "is_ultimate": false,
    "has_upgrade": false,
    "picks": 0.3725047,
    "wins": 0.3810606,
    "win_rate": 0.5085945
  },
  {
    "id": 5090,
    "name": "Crypt Swarm",
    "img": "https://hgv-hyperstone.azurewebsites.net/abilities/death_prophet_carrion_swarm.png",
    "is_ultimate": false,
    "has_upgrade": false,
    "picks": 0.113747649,
    "wins": 0.09015152,
    "win_rate": 0.39403972
  },
  {
    "id": 5218,
    "name": "Poison Attack",
    "img": "https://hgv-hyperstone.azurewebsites.net/abilities/viper_poison_attack.png",
    "is_ultimate": false,
    "has_upgrade": false,
    "picks": 0.349529177,
    "wins": 0.372727275,
    "win_rate": 0.5301724
  },
  {
    "id": 5504,
    "name": "Split Shot",
    "img": "https://hgv-hyperstone.azurewebsites.net/abilities/medusa_split_shot.png",
    "is_ultimate": false,
    "has_upgrade": false,
    "picks": 0.570998132,
    "wins": 0.686363637,
    "win_rate": 0.5976253
  },
  {
    "id": 5506,
    "name": "Mana Shield",
    "img": "https://hgv-hyperstone.azurewebsites.net/abilities/medusa_mana_shield.png",
    "is_ultimate": false,
    "has_upgrade": false,
    "picks": 0.3118644,
    "wins": 0.353787869,
    "win_rate": 0.564009666
  },
  {
    "id": 5136,
    "name": "Sacrifice",
    "img": "https://hgv-hyperstone.azurewebsites.net/abilities/lich_dark_ritual.png",
    "is_ultimate": false,
    "has_upgrade": false,
    "picks": 0.125423729,
    "wins": 0.124242425,
    "win_rate": 0.4924925
  },
  {
    "id": 5357,
    "name": "Earthshock",
    "img": "https://hgv-hyperstone.azurewebsites.net/abilities/ursa_earthshock.png",
    "is_ultimate": false,
    "has_upgrade": false,
    "picks": 0.226742,
    "wins": 0.2060606,
    "win_rate": 0.451827228
  },
  {
    "id": 5156,
    "name": "Take Aim",
    "img": "https://hgv-hyperstone.azurewebsites.net/abilities/sniper_take_aim.png",
    "is_ultimate": false,
    "has_upgrade": false,
    "picks": 0.339736342,
    "wins": 0.3909091,
    "win_rate": 0.5720621
  },
  {
    "id": 5234,
    "name": "Shallow Grave",
    "img": "https://hgv-hyperstone.azurewebsites.net/abilities/dazzle_shallow_grave.png",
    "is_ultimate": false,
    "has_upgrade": true,
    "picks": 0.189830512,
    "wins": 0.170454547,
    "win_rate": 0.446428567
  },
  {
    "id": 5263,
    "name": "Purification",
    "img": "https://hgv-hyperstone.azurewebsites.net/abilities/omniknight_purification.png",
    "is_ultimate": false,
    "has_upgrade": false,
    "picks": 0.1551789,
    "wins": 0.1530303,
    "win_rate": 0.490291268
  },
  {
    "id": 8000,
    "name": "Stroke of Fate",
    "img": "https://hgv-hyperstone.azurewebsites.net/abilities/grimstroke_dark_artistry.png",
    "is_ultimate": false,
    "has_upgrade": false,
    "picks": 0.125047088,
    "wins": 0.111363634,
    "win_rate": 0.442771077
  },
  {
    "id": 8007,
    "name": "Ink Swell",
    "img": "https://hgv-hyperstone.azurewebsites.net/abilities/grimstroke_spirit_walk.png",
    "is_ultimate": false,
    "has_upgrade": false,
    "picks": 0.1645951,
    "wins": 0.153787881,
    "win_rate": 0.4645309
  },
  {
    "id": 5603,
    "name": "Searing Chains",
    "img": "https://hgv-hyperstone.azurewebsites.net/abilities/ember_spirit_searing_chains.png",
    "is_ultimate": false,
    "has_upgrade": false,
    "picks": 0.21694915,
    "wins": 0.226515144,
    "win_rate": 0.5190972
  },
  {
    "id": 5652,
    "name": "Splinter Blast",
    "img": "https://hgv-hyperstone.azurewebsites.net/abilities/winter_wyvern_splinter_blast.png",
    "is_ultimate": false,
    "has_upgrade": false,
    "picks": 0.114124291,
    "wins": 0.08257576,
    "win_rate": 0.359735966
  },
  {
    "id": 5345,
    "name": "Cold Feet",
    "img": "https://hgv-hyperstone.azurewebsites.net/abilities/ancient_apparition_cold_feet.png",
    "is_ultimate": false,
    "has_upgrade": false,
    "picks": 0.185310736,
    "wins": 0.184090912,
    "win_rate": 0.493902445
  },
  {
    "id": 5392,
    "name": "Astral Imprisonment",
    "img": "https://hgv-hyperstone.azurewebsites.net/abilities/obsidian_destroyer_astral_imprisonment.png",
    "is_ultimate": false,
    "has_upgrade": true,
    "picks": 0.11450094,
    "wins": 0.101515152,
    "win_rate": 0.440789461
  },
  {
    "id": 5581,
    "name": "Arcane Bolt",
    "img": "https://hgv-hyperstone.azurewebsites.net/abilities/skywrath_mage_arcane_bolt.png",
    "is_ultimate": false,
    "has_upgrade": false,
    "picks": 0.07457627,
    "wins": 0.07651515,
    "win_rate": 0.510101
  },
  {
    "id": 5184,
    "name": "Time Lock",
    "img": "https://hgv-hyperstone.azurewebsites.net/abilities/faceless_void_time_lock.png",
    "is_ultimate": false,
    "has_upgrade": false,
    "picks": 0.309981167,
    "wins": 0.3090909,
    "win_rate": 0.495747268
  },
  {
    "id": 5468,
    "name": "Ensnare",
    "img": "https://hgv-hyperstone.azurewebsites.net/abilities/naga_siren_ensnare.png",
    "is_ultimate": false,
    "has_upgrade": false,
    "picks": 0.429378539,
    "wins": 0.394696981,
    "win_rate": 0.457017541
  },
  {
    "id": 5297,
    "name": "Dual Breath",
    "img": "https://hgv-hyperstone.azurewebsites.net/abilities/jakiro_dual_breath.png",
    "is_ultimate": false,
    "has_upgrade": false,
    "picks": 0.143502831,
    "wins": 0.1219697,
    "win_rate": 0.422572166
  },
  {
    "id": 5298,
    "name": "Ice Path",
    "img": "https://hgv-hyperstone.azurewebsites.net/abilities/jakiro_ice_path.png",
    "is_ultimate": false,
    "has_upgrade": false,
    "picks": 0.20489642,
    "wins": 0.187878788,
    "win_rate": 0.455882341
  },
  {
    "id": 5362,
    "name": "Homing Missile",
    "img": "https://hgv-hyperstone.azurewebsites.net/abilities/gyrocopter_homing_missile.png",
    "is_ultimate": false,
    "has_upgrade": false,
    "picks": 0.262900174,
    "wins": 0.275,
    "win_rate": 0.5200573
  },
  {
    "id": 5291,
    "name": "Geminate Attack",
    "img": "https://hgv-hyperstone.azurewebsites.net/abilities/weaver_geminate_attack.png",
    "is_ultimate": false,
    "has_upgrade": false,
    "picks": 0.32165724,
    "wins": 0.3121212,
    "win_rate": 0.482435584
  },
  {
    "id": 5519,
    "name": "Empower",
    "img": "https://hgv-hyperstone.azurewebsites.net/abilities/magnataur_empower.png",
    "is_ultimate": false,
    "has_upgrade": false,
    "picks": 0.26629,
    "wins": 0.243181825,
    "win_rate": 0.4540311
  },
  {
    "id": 5190,
    "name": "Stifling Dagger",
    "img": "https://hgv-hyperstone.azurewebsites.net/abilities/phantom_assassin_stifling_dagger.png",
    "is_ultimate": false,
    "has_upgrade": false,
    "picks": 0.23013182,
    "wins": 0.223484844,
    "win_rate": 0.482815057
  },
  {
    "id": 5260,
    "name": "Searing Arrows",
    "img": "https://hgv-hyperstone.azurewebsites.net/abilities/clinkz_searing_arrows.png",
    "is_ultimate": false,
    "has_upgrade": false,
    "picks": 0.242937848,
    "wins": 0.23863636,
    "win_rate": 0.4883721
  },
  {
    "id": 5299,
    "name": "Liquid Fire",
    "img": "https://hgv-hyperstone.azurewebsites.net/abilities/jakiro_liquid_fire.png",
    "is_ultimate": false,
    "has_upgrade": false,
    "picks": 0.309981167,
    "wins": 0.285606056,
    "win_rate": 0.4580802
  },
  {
    "id": 5122,
    "name": "Magic Missile",
    "img": "https://hgv-hyperstone.azurewebsites.net/abilities/vengefulspirit_magic_missile.png",
    "is_ultimate": false,
    "has_upgrade": false,
    "picks": 0.0858757049,
    "wins": 0.0893939361,
    "win_rate": 0.517543852
  },
  {
    "id": 5328,
    "name": "Penitence",
    "img": "https://hgv-hyperstone.azurewebsites.net/abilities/chen_penitence.png",
    "is_ultimate": false,
    "has_upgrade": false,
    "picks": 0.2259887,
    "wins": 0.214393944,
    "win_rate": 0.471666664
  },
  {
    "id": 5227,
    "name": "Dragon Tail",
    "img": "https://hgv-hyperstone.azurewebsites.net/abilities/dragon_knight_dragon_tail.png",
    "is_ultimate": false,
    "has_upgrade": false,
    "picks": 0.145009413,
    "wins": 0.150757581,
    "win_rate": 0.516883135
  },
  {
    "id": 5259,
    "name": "Strafe",
    "img": "https://hgv-hyperstone.azurewebsites.net/abilities/clinkz_strafe.png",
    "is_ultimate": false,
    "has_upgrade": false,
    "picks": 0.329566866,
    "wins": 0.308333337,
    "win_rate": 0.465142846
  },
  {
    "id": 5365,
    "name": "Acid Spray",
    "img": "https://hgv-hyperstone.azurewebsites.net/abilities/alchemist_acid_spray.png",
    "is_ultimate": false,
    "has_upgrade": false,
    "picks": 0.249340862,
    "wins": 0.231818184,
    "win_rate": 0.462235659
  },
  {
    "id": 5127,
    "name": "Frostbite",
    "img": "https://hgv-hyperstone.azurewebsites.net/abilities/crystal_maiden_frostbite.png",
    "is_ultimate": false,
    "has_upgrade": false,
    "picks": 0.09114878,
    "wins": 0.08712121,
    "win_rate": 0.4752066
  },
  {
    "id": 5219,
    "name": "Nethertoxin",
    "img": "https://hgv-hyperstone.azurewebsites.net/abilities/viper_nethertoxin.png",
    "is_ultimate": false,
    "has_upgrade": false,
    "picks": 0.282109231,
    "wins": 0.274242431,
    "win_rate": 0.4833111
  },
  {
    "id": 5224,
    "name": "Lunar Blessing",
    "img": "https://hgv-hyperstone.azurewebsites.net/abilities/luna_lunar_blessing.png",
    "is_ultimate": false,
    "has_upgrade": false,
    "picks": 0.241431266,
    "wins": 0.25454545,
    "win_rate": 0.524180949
  },
  {
    "id": 5334,
    "name": "Spectral Dagger",
    "img": "https://hgv-hyperstone.azurewebsites.net/abilities/spectre_spectral_dagger.png",
    "is_ultimate": false,
    "has_upgrade": false,
    "picks": 0.3408663,
    "wins": 0.335606068,
    "win_rate": 0.489502758
  },
  {
    "id": 5335,
    "name": "Desolate",
    "img": "https://hgv-hyperstone.azurewebsites.net/abilities/spectre_desolate.png",
    "is_ultimate": false,
    "has_upgrade": false,
    "picks": 0.5928437,
    "wins": 0.585606039,
    "win_rate": 0.491105467
  },
  {
    "id": 5480,
    "name": "Grave Chill",
    "img": "https://hgv-hyperstone.azurewebsites.net/abilities/visage_grave_chill.png",
    "is_ultimate": false,
    "has_upgrade": false,
    "picks": 0.505838037,
    "wins": 0.4840909,
    "win_rate": 0.475800455
  },
  {
    "id": 5029,
    "name": "Healing Ward",
    "img": "https://hgv-hyperstone.azurewebsites.net/abilities/juggernaut_healing_ward.png",
    "is_ultimate": false,
    "has_upgrade": false,
    "picks": 0.1984934,
    "wins": 0.231818184,
    "win_rate": 0.580645144
  },
  {
    "id": 5079,
    "name": "Hex",
    "img": "https://hgv-hyperstone.azurewebsites.net/abilities/shadow_shaman_voodoo.png",
    "is_ultimate": false,
    "has_upgrade": false,
    "picks": 0.3709981,
    "wins": 0.381818175,
    "win_rate": 0.5116751
  },
  {
    "id": 5024,
    "name": "Enchant Totem",
    "img": "https://hgv-hyperstone.azurewebsites.net/abilities/earthshaker_enchant_totem.png",
    "is_ultimate": false,
    "has_upgrade": true,
    "picks": 0.138229758,
    "wins": 0.118181817,
    "win_rate": 0.4250681
  },
  {
    "id": 5582,
    "name": "Concussive Shot",
    "img": "https://hgv-hyperstone.azurewebsites.net/abilities/skywrath_mage_concussive_shot.png",
    "is_ultimate": false,
    "has_upgrade": false,
    "picks": 0.189077213,
    "wins": 0.181818187,
    "win_rate": 0.478087664
  },
  {
    "id": 5124,
    "name": "Wave of Terror",
    "img": "https://hgv-hyperstone.azurewebsites.net/abilities/vengefulspirit_wave_of_terror.png",
    "is_ultimate": false,
    "has_upgrade": false,
    "picks": 0.2007533,
    "wins": 0.202272728,
    "win_rate": 0.500938058
  },
  {
    "id": 5155,
    "name": "Headshot",
    "img": "https://hgv-hyperstone.azurewebsites.net/abilities/sniper_headshot.png",
    "is_ultimate": false,
    "has_upgrade": false,
    "picks": 0.459887,
    "wins": 0.455303043,
    "win_rate": 0.492219478
  },
  {
    "id": 5250,
    "name": "Feast",
    "img": "https://hgv-hyperstone.azurewebsites.net/abilities/life_stealer_feast.png",
    "is_ultimate": false,
    "has_upgrade": false,
    "picks": 0.154048964,
    "wins": 0.179545447,
    "win_rate": 0.5794621
  },
  {
    "id": 5116,
    "name": "Bash of the Deep",
    "img": "https://hgv-hyperstone.azurewebsites.net/abilities/slardar_bash.png",
    "is_ultimate": false,
    "has_upgrade": false,
    "picks": 0.3126177,
    "wins": 0.3037879,
    "win_rate": 0.483132541
  },
  {
    "id": 5249,
    "name": "Rage",
    "img": "https://hgv-hyperstone.azurewebsites.net/abilities/life_stealer_rage.png",
    "is_ultimate": false,
    "has_upgrade": false,
    "picks": 0.123163842,
    "wins": 0.135606065,
    "win_rate": 0.5474006
  },
  {
    "id": 5354,
    "name": "Empowering Haste",
    "img": "https://hgv-hyperstone.azurewebsites.net/abilities/spirit_breaker_empowering_haste.png",
    "is_ultimate": false,
    "has_upgrade": false,
    "picks": 0.453484,
    "wins": 0.473484844,
    "win_rate": 0.519103
  },
  {
    "id": 6344,
    "name": "Swashbuckle",
    "img": "https://hgv-hyperstone.azurewebsites.net/abilities/pangolier_swashbuckle.png",
    "is_ultimate": false,
    "has_upgrade": false,
    "picks": 0.271939725,
    "wins": 0.292424232,
    "win_rate": 0.534626067
  },
  {
    "id": 5245,
    "name": "Sprout",
    "img": "https://hgv-hyperstone.azurewebsites.net/abilities/furion_sprout.png",
    "is_ultimate": false,
    "has_upgrade": false,
    "picks": 0.307344645,
    "wins": 0.316666663,
    "win_rate": 0.5122549
  },
  {
    "id": 5496,
    "name": "Essence Shift",
    "img": "https://hgv-hyperstone.azurewebsites.net/abilities/slark_essence_shift.png",
    "is_ultimate": false,
    "has_upgrade": false,
    "picks": 0.338606417,
    "wins": 0.3598485,
    "win_rate": 0.528364837
  },
  {
    "id": 5042,
    "name": "Fiery Soul",
    "img": "https://hgv-hyperstone.azurewebsites.net/abilities/lina_fiery_soul.png",
    "is_ultimate": false,
    "has_upgrade": false,
    "picks": 0.20263654,
    "wins": 0.204545453,
    "win_rate": 0.5018587
  },
  {
    "id": 5264,
    "name": "Repel",
    "img": "https://hgv-hyperstone.azurewebsites.net/abilities/omniknight_repel.png",
    "is_ultimate": false,
    "has_upgrade": false,
    "picks": 0.296045184,
    "wins": 0.293939382,
    "win_rate": 0.493638664
  },
  {
    "id": 5597,
    "name": "Moment of Courage",
    "img": "https://hgv-hyperstone.azurewebsites.net/abilities/legion_commander_moment_of_courage.png",
    "is_ultimate": false,
    "has_upgrade": false,
    "picks": 0.319774,
    "wins": 0.2977273,
    "win_rate": 0.462897539
  },
  {
    "id": 5494,
    "name": "Dark Pact",
    "img": "https://hgv-hyperstone.azurewebsites.net/abilities/slark_dark_pact.png",
    "is_ultimate": false,
    "has_upgrade": false,
    "picks": 0.2259887,
    "wins": 0.1969697,
    "win_rate": 0.433333337
  },
  {
    "id": 5041,
    "name": "Light Strike Array",
    "img": "https://hgv-hyperstone.azurewebsites.net/abilities/lina_light_strike_array.png",
    "is_ultimate": false,
    "has_upgrade": false,
    "picks": 0.187193975,
    "wins": 0.174242422,
    "win_rate": 0.462776661
  },
  {
    "id": 5021,
    "name": "Precision Aura",
    "img": "https://hgv-hyperstone.azurewebsites.net/abilities/drow_ranger_trueshot.png",
    "is_ultimate": false,
    "has_upgrade": false,
    "picks": 0.297551781,
    "wins": 0.307575762,
    "win_rate": 0.513924062
  },
  {
    "id": 5257,
    "name": "Surge",
    "img": "https://hgv-hyperstone.azurewebsites.net/abilities/dark_seer_surge.png",
    "is_ultimate": false,
    "has_upgrade": false,
    "picks": 0.239548028,
    "wins": 0.223484844,
    "win_rate": 0.4638365
  },
  {
    "id": 5440,
    "name": "Bloodlust",
    "img": "https://hgv-hyperstone.azurewebsites.net/abilities/ogre_magi_bloodlust.png",
    "is_ultimate": false,
    "has_upgrade": false,
    "picks": 0.198116764,
    "wins": 0.184848487,
    "win_rate": 0.463878334
  },
  {
    "id": 5114,
    "name": "Guardian Sprint",
    "img": "https://hgv-hyperstone.azurewebsites.net/abilities/slardar_sprint.png",
    "is_ultimate": false,
    "has_upgrade": false,
    "picks": 0.3755179,
    "wins": 0.394696981,
    "win_rate": 0.5225677
  },
  {
    "id": 5233,
    "name": "Poison Touch",
    "img": "https://hgv-hyperstone.azurewebsites.net/abilities/dazzle_poison_touch.png",
    "is_ultimate": false,
    "has_upgrade": false,
    "picks": 0.281355917,
    "wins": 0.24166666,
    "win_rate": 0.4270415
  },
  {
    "id": 5459,
    "name": "Glimpse",
    "img": "https://hgv-hyperstone.azurewebsites.net/abilities/disruptor_glimpse.png",
    "is_ultimate": false,
    "has_upgrade": false,
    "picks": 0.161205277,
    "wins": 0.155303031,
    "win_rate": 0.478971958
  },
  {
    "id": 5358,
    "name": "Overpower",
    "img": "https://hgv-hyperstone.azurewebsites.net/abilities/ursa_overpower.png",
    "is_ultimate": false,
    "has_upgrade": false,
    "picks": 0.177401125,
    "wins": 0.165151522,
    "win_rate": 0.462845
  },
  {
    "id": 5016,
    "name": "Blood Rite",
    "img": "https://hgv-hyperstone.azurewebsites.net/abilities/bloodseeker_blood_bath.png",
    "is_ultimate": false,
    "has_upgrade": false,
    "picks": 0.241431266,
    "wins": 0.226515144,
    "win_rate": 0.466458648
  },
  {
    "id": 5442,
    "name": "Decay",
    "img": "https://hgv-hyperstone.azurewebsites.net/abilities/undying_decay.png",
    "is_ultimate": false,
    "has_upgrade": true,
    "picks": 0.0847457647,
    "wins": 0.0734848455,
    "win_rate": 0.4311111
  },
  {
    "id": 5526,
    "name": "Reactive Armor",
    "img": "https://hgv-hyperstone.azurewebsites.net/abilities/shredder_reactive_armor.png",
    "is_ultimate": false,
    "has_upgrade": false,
    "picks": 0.118644066,
    "wins": 0.121212125,
    "win_rate": 0.507936537
  },
  {
    "id": 5255,
    "name": "Vacuum",
    "img": "https://hgv-hyperstone.azurewebsites.net/abilities/dark_seer_vacuum.png",
    "is_ultimate": false,
    "has_upgrade": false,
    "picks": 0.08700565,
    "wins": 0.06818182,
    "win_rate": 0.38961038
  },
  {
    "id": 8006,
    "name": "Phantom's Embrace",
    "img": "https://hgv-hyperstone.azurewebsites.net/abilities/grimstroke_ink_creature.png",
    "is_ultimate": false,
    "has_upgrade": false,
    "picks": 0.216572508,
    "wins": 0.204545453,
    "win_rate": 0.4695652
  },
  {
    "id": 5005,
    "name": "Spell Shield",
    "img": "https://hgv-hyperstone.azurewebsites.net/abilities/antimage_spell_shield.png",
    "is_ultimate": false,
    "has_upgrade": true,
    "picks": 0.20489642,
    "wins": 0.193181813,
    "win_rate": 0.46875
  },
  {
    "id": 5188,
    "name": "Nether Ward",
    "img": "https://hgv-hyperstone.azurewebsites.net/abilities/pugna_nether_ward.png",
    "is_ultimate": false,
    "has_upgrade": false,
    "picks": 0.176647827,
    "wins": 0.193181813,
    "win_rate": 0.54371
  },
  {
    "id": 5251,
    "name": "Open Wounds",
    "img": "https://hgv-hyperstone.azurewebsites.net/abilities/life_stealer_open_wounds.png",
    "is_ultimate": false,
    "has_upgrade": false,
    "picks": 0.247457623,
    "wins": 0.213636369,
    "win_rate": 0.429223746
  },
  {
    "id": 5111,
    "name": "Lightning Bolt",
    "img": "https://hgv-hyperstone.azurewebsites.net/abilities/zuus_lightning_bolt.png",
    "is_ultimate": false,
    "has_upgrade": false,
    "picks": 0.05009416,
    "wins": 0.0363636352,
    "win_rate": 0.36090225
  },
  {
    "id": 5401,
    "name": "Drunken Haze",
    "img": "https://hgv-hyperstone.azurewebsites.net/abilities/brewmaster_drunken_haze.png",
    "is_ultimate": false,
    "has_upgrade": false,
    "picks": 0.22787194,
    "wins": 0.2,
    "win_rate": 0.436363637
  },
  {
    "id": 5677,
    "name": "Flux",
    "img": "https://hgv-hyperstone.azurewebsites.net/abilities/arc_warden_flux.png",
    "is_ultimate": false,
    "has_upgrade": false,
    "picks": 0.14877589,
    "wins": 0.148484856,
    "win_rate": 0.496202528
  },
  {
    "id": 5096,
    "name": "Warcry",
    "img": "https://hgv-hyperstone.azurewebsites.net/abilities/sven_warcry.png",
    "is_ultimate": false,
    "has_upgrade": false,
    "picks": 0.369114876,
    "wins": 0.3469697,
    "win_rate": 0.467346936
  },
  {
    "id": 5103,
    "name": "Sand Storm",
    "img": "https://hgv-hyperstone.azurewebsites.net/abilities/sandking_sand_storm.png",
    "is_ultimate": false,
    "has_upgrade": false,
    "picks": 0.163841814,
    "wins": 0.140151516,
    "win_rate": 0.425287366
  },
  {
    "id": 5028,
    "name": "Blade Fury",
    "img": "https://hgv-hyperstone.azurewebsites.net/abilities/juggernaut_blade_fury.png",
    "is_ultimate": false,
    "has_upgrade": false,
    "picks": 0.149152547,
    "wins": 0.161363631,
    "win_rate": 0.5378788
  },
  {
    "id": 5428,
    "name": "Chaos Strike",
    "img": "https://hgv-hyperstone.azurewebsites.net/abilities/chaos_knight_chaos_strike.png",
    "is_ultimate": false,
    "has_upgrade": false,
    "picks": 0.4015066,
    "wins": 0.398484856,
    "win_rate": 0.4934334
  },
  {
    "id": 6342,
    "name": "Cursed Crown",
    "img": "https://hgv-hyperstone.azurewebsites.net/abilities/dark_willow_cursed_crown.png",
    "is_ultimate": false,
    "has_upgrade": false,
    "picks": 0.180037662,
    "wins": 0.1659091,
    "win_rate": 0.458159
  },
  {
    "id": 5131,
    "name": "Powershot",
    "img": "https://hgv-hyperstone.azurewebsites.net/abilities/windrunner_powershot.png",
    "is_ultimate": false,
    "has_upgrade": false,
    "picks": 0.174387947,
    "wins": 0.159848481,
    "win_rate": 0.455723554
  },
  {
    "id": 5267,
    "name": "Untouchable",
    "img": "https://hgv-hyperstone.azurewebsites.net/abilities/enchantress_untouchable.png",
    "is_ultimate": false,
    "has_upgrade": false,
    "picks": 0.249340862,
    "wins": 0.259848475,
    "win_rate": 0.5181269
  },
  {
    "id": 5048,
    "name": "Sacred Arrow",
    "img": "https://hgv-hyperstone.azurewebsites.net/abilities/mirana_arrow.png",
    "is_ultimate": false,
    "has_upgrade": false,
    "picks": 0.287005663,
    "wins": 0.319696963,
    "win_rate": 0.553805768
  },
  {
    "id": 5195,
    "name": "Meld",
    "img": "https://hgv-hyperstone.azurewebsites.net/abilities/templar_assassin_meld.png",
    "is_ultimate": false,
    "has_upgrade": false,
    "picks": 0.2817326,
    "wins": 0.280303031,
    "win_rate": 0.49465242
  },
  {
    "id": 5032,
    "name": "Tidebringer",
    "img": "https://hgv-hyperstone.azurewebsites.net/abilities/kunkka_tidebringer.png",
    "is_ultimate": false,
    "has_upgrade": false,
    "picks": 0.163841814,
    "wins": 0.148484856,
    "win_rate": 0.450574726
  },
  {
    "id": 5050,
    "name": "Leap",
    "img": "https://hgv-hyperstone.azurewebsites.net/abilities/mirana_leap.png",
    "is_ultimate": false,
    "has_upgrade": false,
    "picks": 0.389077216,
    "wins": 0.4280303,
    "win_rate": 0.546950638
  },
  {
    "id": 5246,
    "name": "Teleportation",
    "img": "https://hgv-hyperstone.azurewebsites.net/abilities/furion_teleportation.png",
    "is_ultimate": false,
    "has_upgrade": false,
    "picks": 0.243691146,
    "wins": 0.258333325,
    "win_rate": 0.527047932
  },
  {
    "id": 5620,
    "name": "Conjure Image",
    "img": "https://hgv-hyperstone.azurewebsites.net/abilities/terrorblade_conjure_image.png",
    "is_ultimate": false,
    "has_upgrade": false,
    "picks": 0.439924657,
    "wins": 0.4287879,
    "win_rate": 0.48458904
  },
  {
    "id": 5623,
    "name": "Icarus Dive",
    "img": "https://hgv-hyperstone.azurewebsites.net/abilities/phoenix_icarus_dive.png",
    "is_ultimate": false,
    "has_upgrade": false,
    "picks": 0.106214687,
    "wins": 0.1,
    "win_rate": 0.4680851
  },
  {
    "id": 5120,
    "name": "Anchor Smash",
    "img": "https://hgv-hyperstone.azurewebsites.net/abilities/tidehunter_anchor_smash.png",
    "is_ultimate": false,
    "has_upgrade": false,
    "picks": 0.184557438,
    "wins": 0.162878782,
    "win_rate": 0.4387755
  },
  {
    "id": 5040,
    "name": "Dragon Slave",
    "img": "https://hgv-hyperstone.azurewebsites.net/abilities/lina_dragon_slave.png",
    "is_ultimate": false,
    "has_upgrade": false,
    "picks": 0.15969868,
    "wins": 0.138636366,
    "win_rate": 0.43160376
  },
  {
    "id": 5095,
    "name": "Great Cleave",
    "img": "https://hgv-hyperstone.azurewebsites.net/abilities/sven_great_cleave.png",
    "is_ultimate": false,
    "has_upgrade": false,
    "picks": 0.3269303,
    "wins": 0.323484838,
    "win_rate": 0.4919355
  },
  {
    "id": 5235,
    "name": "Shadow Wave",
    "img": "https://hgv-hyperstone.azurewebsites.net/abilities/dazzle_shadow_wave.png",
    "is_ultimate": false,
    "has_upgrade": false,
    "picks": 0.280602634,
    "wins": 0.261363626,
    "win_rate": 0.463087261
  },
  {
    "id": 5091,
    "name": "Silence",
    "img": "https://hgv-hyperstone.azurewebsites.net/abilities/death_prophet_silence.png",
    "is_ultimate": false,
    "has_upgrade": false,
    "picks": 0.156308845,
    "wins": 0.142424241,
    "win_rate": 0.453012049
  },
  {
    "id": 5099,
    "name": "Electric Vortex",
    "img": "https://hgv-hyperstone.azurewebsites.net/abilities/storm_spirit_electric_vortex.png",
    "is_ultimate": false,
    "has_upgrade": true,
    "picks": 0.158945382,
    "wins": 0.152272731,
    "win_rate": 0.4763033
  },
  {
    "id": 5135,
    "name": "Ice Armor",
    "img": "https://hgv-hyperstone.azurewebsites.net/abilities/lich_frost_armor.png",
    "is_ultimate": false,
    "has_upgrade": false,
    "picks": 0.1386064,
    "wins": 0.125757575,
    "win_rate": 0.451086968
  },
  {
    "id": 5268,
    "name": "Enchant",
    "img": "https://hgv-hyperstone.azurewebsites.net/abilities/enchantress_enchant.png",
    "is_ultimate": false,
    "has_upgrade": false,
    "picks": 0.161205277,
    "wins": 0.146969691,
    "win_rate": 0.453271031
  },
  {
    "id": 5238,
    "name": "Power Cogs",
    "img": "https://hgv-hyperstone.azurewebsites.net/abilities/rattletrap_power_cogs.png",
    "is_ultimate": false,
    "has_upgrade": false,
    "picks": 0.221092284,
    "wins": 0.205303028,
    "win_rate": 0.4616695
  },
  {
    "id": 5285,
    "name": "Shuriken Toss",
    "img": "https://hgv-hyperstone.azurewebsites.net/abilities/bounty_hunter_shuriken_toss.png",
    "is_ultimate": false,
    "has_upgrade": true,
    "picks": 0.135969862,
    "wins": 0.115151517,
    "win_rate": 0.421052635
  },
  {
    "id": 5651,
    "name": "Arctic Burn",
    "img": "https://hgv-hyperstone.azurewebsites.net/abilities/winter_wyvern_arctic_burn.png",
    "is_ultimate": false,
    "has_upgrade": true,
    "picks": 0.194350287,
    "wins": 0.223484844,
    "win_rate": 0.5717054
  },
  {
    "id": 5272,
    "name": "Burning Spear",
    "img": "https://hgv-hyperstone.azurewebsites.net/abilities/huskar_burning_spear.png",
    "is_ultimate": false,
    "has_upgrade": false,
    "picks": 0.265536726,
    "wins": 0.25454545,
    "win_rate": 0.476595759
  },
  {
    "id": 5377,
    "name": "Arcane Curse",
    "img": "https://hgv-hyperstone.azurewebsites.net/abilities/silencer_curse_of_the_silent.png",
    "is_ultimate": false,
    "has_upgrade": false,
    "picks": 0.152542368,
    "wins": 0.144696966,
    "win_rate": 0.471604943
  },
  {
    "id": 5346,
    "name": "Ice Vortex",
    "img": "https://hgv-hyperstone.azurewebsites.net/abilities/ancient_apparition_ice_vortex.png",
    "is_ultimate": false,
    "has_upgrade": false,
    "picks": 0.06629002,
    "wins": 0.0568181835,
    "win_rate": 0.426136374
  },
  {
    "id": 5355,
    "name": "Greater Bash",
    "img": "https://hgv-hyperstone.azurewebsites.net/abilities/spirit_breaker_greater_bash.png",
    "is_ultimate": false,
    "has_upgrade": false,
    "picks": 0.282109231,
    "wins": 0.2719697,
    "win_rate": 0.479305744
  },
  {
    "id": 5277,
    "name": "Hunter in the Night",
    "img": "https://hgv-hyperstone.azurewebsites.net/abilities/night_stalker_hunter_in_the_night.png",
    "is_ultimate": false,
    "has_upgrade": false,
    "picks": 0.236534834,
    "wins": 0.2439394,
    "win_rate": 0.5127388
  },
  {
    "id": 5361,
    "name": "Rocket Barrage",
    "img": "https://hgv-hyperstone.azurewebsites.net/abilities/gyrocopter_rocket_barrage.png",
    "is_ultimate": false,
    "has_upgrade": false,
    "picks": 0.151412427,
    "wins": 0.134090915,
    "win_rate": 0.4402985
  },
  {
    "id": 5625,
    "name": "Fire Spirits",
    "img": "https://hgv-hyperstone.azurewebsites.net/abilities/phoenix_fire_spirits.png",
    "is_ultimate": false,
    "has_upgrade": false,
    "picks": 0.0293785315,
    "wins": 0.0242424235,
    "win_rate": 0.410256416
  },
  {
    "id": 5017,
    "name": "Thirst",
    "img": "https://hgv-hyperstone.azurewebsites.net/abilities/bloodseeker_thirst.png",
    "is_ultimate": false,
    "has_upgrade": false,
    "picks": 0.186440676,
    "wins": 0.2060606,
    "win_rate": 0.5494949
  },
  {
    "id": 5163,
    "name": "Shadow Word",
    "img": "https://hgv-hyperstone.azurewebsites.net/abilities/warlock_shadow_word.png",
    "is_ultimate": false,
    "has_upgrade": false,
    "picks": 0.128060266,
    "wins": 0.108333334,
    "win_rate": 0.420588225
  },
  {
    "id": 5261,
    "name": "Skeleton Walk",
    "img": "https://hgv-hyperstone.azurewebsites.net/abilities/clinkz_wind_walk.png",
    "is_ultimate": false,
    "has_upgrade": false,
    "picks": 0.14538607,
    "wins": 0.1621212,
    "win_rate": 0.55440414
  },
  {
    "id": 5019,
    "name": "Frost Arrows",
    "img": "https://hgv-hyperstone.azurewebsites.net/abilities/drow_ranger_frost_arrows.png",
    "is_ultimate": false,
    "has_upgrade": false,
    "picks": 0.413935959,
    "wins": 0.3840909,
    "win_rate": 0.461328477
  },
  {
    "id": 5074,
    "name": "Flesh Heap",
    "img": "https://hgv-hyperstone.azurewebsites.net/abilities/pudge_flesh_heap.png",
    "is_ultimate": false,
    "has_upgrade": false,
    "picks": 0.159322038,
    "wins": 0.1560606,
    "win_rate": 0.486997634
  },
  {
    "id": 5045,
    "name": "Hex",
    "img": "https://hgv-hyperstone.azurewebsites.net/abilities/lion_voodoo.png",
    "is_ultimate": false,
    "has_upgrade": false,
    "picks": 0.328813553,
    "wins": 0.314393938,
    "win_rate": 0.475372285
  },
  {
    "id": 5123,
    "name": "Vengeance Aura",
    "img": "https://hgv-hyperstone.azurewebsites.net/abilities/vengefulspirit_command_aura.png",
    "is_ultimate": false,
    "has_upgrade": false,
    "picks": 0.2779661,
    "wins": 0.36742425,
    "win_rate": 0.657181561
  },
  {
    "id": 5481,
    "name": "Soul Assumption",
    "img": "https://hgv-hyperstone.azurewebsites.net/abilities/visage_soul_assumption.png",
    "is_ultimate": false,
    "has_upgrade": false,
    "picks": 0.105838038,
    "wins": 0.0848484859,
    "win_rate": 0.3985765
  },
  {
    "id": 5083,
    "name": "Static Link",
    "img": "https://hgv-hyperstone.azurewebsites.net/abilities/razor_static_link.png",
    "is_ultimate": false,
    "has_upgrade": false,
    "picks": 0.316007525,
    "wins": 0.270454556,
    "win_rate": 0.425506562
  },
  {
    "id": 5112,
    "name": "Static Field",
    "img": "https://hgv-hyperstone.azurewebsites.net/abilities/zuus_static_field.png",
    "is_ultimate": false,
    "has_upgrade": false,
    "picks": 0.05235405,
    "wins": 0.0492424257,
    "win_rate": 0.4676259
  },
  {
    "id": 5548,
    "name": "Viscous Nasal Goo",
    "img": "https://hgv-hyperstone.azurewebsites.net/abilities/bristleback_viscous_nasal_goo.png",
    "is_ultimate": false,
    "has_upgrade": true,
    "picks": 0.178154424,
    "wins": 0.152272731,
    "win_rate": 0.424947143
  },
  {
    "id": 5014,
    "name": "Nightmare",
    "img": "https://hgv-hyperstone.azurewebsites.net/abilities/bane_nightmare.png",
    "is_ultimate": false,
    "has_upgrade": false,
    "picks": 0.128813565,
    "wins": 0.118939392,
    "win_rate": 0.459064335
  },
  {
    "id": 5051,
    "name": "Starstorm",
    "img": "https://hgv-hyperstone.azurewebsites.net/abilities/mirana_starfall.png",
    "is_ultimate": false,
    "has_upgrade": true,
    "picks": 0.08964218,
    "wins": 0.0848484859,
    "win_rate": 0.470588237
  },
  {
    "id": 5220,
    "name": "Corrosive Skin",
    "img": "https://hgv-hyperstone.azurewebsites.net/abilities/viper_corrosive_skin.png",
    "is_ultimate": false,
    "has_upgrade": false,
    "picks": 0.274952918,
    "wins": 0.293939382,
    "win_rate": 0.531506836
  },
  {
    "id": 5023,
    "name": "Fissure",
    "img": "https://hgv-hyperstone.azurewebsites.net/abilities/earthshaker_fissure.png",
    "is_ultimate": false,
    "has_upgrade": false,
    "picks": 0.16082862,
    "wins": 0.154545456,
    "win_rate": 0.477751762
  },
  {
    "id": 5256,
    "name": "Ion Shell",
    "img": "https://hgv-hyperstone.azurewebsites.net/abilities/dark_seer_ion_shell.png",
    "is_ultimate": false,
    "has_upgrade": false,
    "picks": 0.117890775,
    "wins": 0.09924243,
    "win_rate": 0.418530345
  },
  {
    "id": 5182,
    "name": "Time Walk",
    "img": "https://hgv-hyperstone.azurewebsites.net/abilities/faceless_void_time_walk.png",
    "is_ultimate": false,
    "has_upgrade": false,
    "picks": 0.241807908,
    "wins": 0.24166666,
    "win_rate": 0.496884733
  },
  {
    "id": 5549,
    "name": "Quill Spray",
    "img": "https://hgv-hyperstone.azurewebsites.net/abilities/bristleback_quill_spray.png",
    "is_ultimate": false,
    "has_upgrade": false,
    "picks": 0.0858757049,
    "wins": 0.06969697,
    "win_rate": 0.403508782
  },
  {
    "id": 5638,
    "name": "Fate's Edict",
    "img": "https://hgv-hyperstone.azurewebsites.net/abilities/oracle_fates_edict.png",
    "is_ultimate": false,
    "has_upgrade": false,
    "picks": 0.1047081,
    "wins": 0.09621212,
    "win_rate": 0.456834525
  },
  {
    "id": 5126,
    "name": "Crystal Nova",
    "img": "https://hgv-hyperstone.azurewebsites.net/abilities/crystal_maiden_crystal_nova.png",
    "is_ultimate": false,
    "has_upgrade": false,
    "picks": 0.211676076,
    "wins": 0.221212119,
    "win_rate": 0.519573
  },
  {
    "id": 5550,
    "name": "Bristleback",
    "img": "https://hgv-hyperstone.azurewebsites.net/abilities/bristleback_bristleback.png",
    "is_ultimate": false,
    "has_upgrade": false,
    "picks": 0.166854993,
    "wins": 0.1530303,
    "win_rate": 0.45598194
  },
  {
    "id": 5134,
    "name": "Frost Blast",
    "img": "https://hgv-hyperstone.azurewebsites.net/abilities/lich_frost_nova.png",
    "is_ultimate": false,
    "has_upgrade": false,
    "picks": 0.136723161,
    "wins": 0.106818184,
    "win_rate": 0.388429761
  },
  {
    "id": 5265,
    "name": "Degen Aura",
    "img": "https://hgv-hyperstone.azurewebsites.net/abilities/omniknight_degen_aura.png",
    "is_ultimate": false,
    "has_upgrade": false,
    "picks": 0.46478343,
    "wins": 0.470454544,
    "win_rate": 0.5032415
  },
  {
    "id": 5191,
    "name": "Phantom Strike",
    "img": "https://hgv-hyperstone.azurewebsites.net/abilities/phantom_assassin_phantom_strike.png",
    "is_ultimate": false,
    "has_upgrade": false,
    "picks": 0.266666681,
    "wins": 0.2689394,
    "win_rate": 0.501412451
  },
  {
    "id": 5033,
    "name": "X Marks the Spot",
    "img": "https://hgv-hyperstone.azurewebsites.net/abilities/kunkka_x_marks_the_spot.png",
    "is_ultimate": false,
    "has_upgrade": false,
    "picks": 0.15969868,
    "wins": 0.143181816,
    "win_rate": 0.4457547
  },
  {
    "id": 5138,
    "name": "Paralyzing Cask",
    "img": "https://hgv-hyperstone.azurewebsites.net/abilities/witch_doctor_paralyzing_cask.png",
    "is_ultimate": false,
    "has_upgrade": false,
    "picks": 0.198870063,
    "wins": 0.190151513,
    "win_rate": 0.475378782
  },
  {
    "id": 5142,
    "name": "Smoke Screen",
    "img": "https://hgv-hyperstone.azurewebsites.net/abilities/riki_smoke_screen.png",
    "is_ultimate": false,
    "has_upgrade": false,
    "picks": 0.341242939,
    "wins": 0.3318182,
    "win_rate": 0.4834437
  },
  {
    "id": 5402,
    "name": "Drunken Brawler",
    "img": "https://hgv-hyperstone.azurewebsites.net/abilities/brewmaster_drunken_brawler.png",
    "is_ultimate": false,
    "has_upgrade": false,
    "picks": 0.2772128,
    "wins": 0.288636357,
    "win_rate": 0.517663062
  },
  {
    "id": 5076,
    "name": "Rot",
    "img": "https://hgv-hyperstone.azurewebsites.net/abilities/pudge_rot.png",
    "is_ultimate": false,
    "has_upgrade": false,
    "picks": 0.0625235438,
    "wins": 0.0484848469,
    "win_rate": 0.385542154
  },
  {
    "id": 5511,
    "name": "Fervor",
    "img": "https://hgv-hyperstone.azurewebsites.net/abilities/troll_warlord_fervor.png",
    "is_ultimate": false,
    "has_upgrade": false,
    "picks": 0.172128066,
    "wins": 0.181818187,
    "win_rate": 0.5251641
  },
  {
    "id": 6461,
    "name": "Shield Crash",
    "img": "https://hgv-hyperstone.azurewebsites.net/abilities/pangolier_shield_crash.png",
    "is_ultimate": false,
    "has_upgrade": false,
    "picks": 0.2007533,
    "wins": 0.207575753,
    "win_rate": 0.5140713
  },
  {
    "id": 5044,
    "name": "Earth Spike",
    "img": "https://hgv-hyperstone.azurewebsites.net/abilities/lion_impale.png",
    "is_ultimate": false,
    "has_upgrade": false,
    "picks": 0.1126177,
    "wins": 0.115909092,
    "win_rate": 0.5117057
  },
  {
    "id": 5222,
    "name": "Lucent Beam",
    "img": "https://hgv-hyperstone.azurewebsites.net/abilities/luna_lucent_beam.png",
    "is_ultimate": false,
    "has_upgrade": false,
    "picks": 0.136723161,
    "wins": 0.12954545,
    "win_rate": 0.471074373
  },
  {
    "id": 5082,
    "name": "Plasma Field",
    "img": "https://hgv-hyperstone.azurewebsites.net/abilities/razor_plasma_field.png",
    "is_ultimate": false,
    "has_upgrade": false,
    "picks": 0.176647827,
    "wins": 0.181060612,
    "win_rate": 0.509594858
  },
  {
    "id": 5426,
    "name": "Chaos Bolt",
    "img": "https://hgv-hyperstone.azurewebsites.net/abilities/chaos_knight_chaos_bolt.png",
    "is_ultimate": false,
    "has_upgrade": false,
    "picks": 0.140489638,
    "wins": 0.142424241,
    "win_rate": 0.504021466
  },
  {
    "id": 5151,
    "name": "Heat-Seeking Missile",
    "img": "https://hgv-hyperstone.azurewebsites.net/abilities/tinker_heat_seeking_missile.png",
    "is_ultimate": false,
    "has_upgrade": true,
    "picks": 0.0606403,
    "wins": 0.0484848469,
    "win_rate": 0.397515535
  },
  {
    "id": 5012,
    "name": "Enfeeble",
    "img": "https://hgv-hyperstone.azurewebsites.net/abilities/bane_enfeeble.png",
    "is_ultimate": false,
    "has_upgrade": false,
    "picks": 0.125047088,
    "wins": 0.106818184,
    "win_rate": 0.4246988
  },
  {
    "id": 5396,
    "name": "Howl",
    "img": "https://hgv-hyperstone.azurewebsites.net/abilities/lycan_howl.png",
    "is_ultimate": false,
    "has_upgrade": false,
    "picks": 0.308474571,
    "wins": 0.286363631,
    "win_rate": 0.461538464
  },
  {
    "id": 5359,
    "name": "Fury Swipes",
    "img": "https://hgv-hyperstone.azurewebsites.net/abilities/ursa_fury_swipes.png",
    "is_ultimate": false,
    "has_upgrade": false,
    "picks": 0.188323915,
    "wins": 0.2090909,
    "win_rate": 0.552
  },
  {
    "id": 5320,
    "name": "Sticky Napalm",
    "img": "https://hgv-hyperstone.azurewebsites.net/abilities/batrider_sticky_napalm.png",
    "is_ultimate": false,
    "has_upgrade": false,
    "picks": 0.073446326,
    "wins": 0.05909091,
    "win_rate": 0.4
  },
  {
    "id": 5322,
    "name": "Firefly",
    "img": "https://hgv-hyperstone.azurewebsites.net/abilities/batrider_firefly.png",
    "is_ultimate": false,
    "has_upgrade": false,
    "picks": 0.166478336,
    "wins": 0.140909091,
    "win_rate": 0.420814484
  },
  {
    "id": 5565,
    "name": "Ice Shards",
    "img": "https://hgv-hyperstone.azurewebsites.net/abilities/tusk_ice_shards.png",
    "is_ultimate": false,
    "has_upgrade": false,
    "picks": 0.193596989,
    "wins": 0.181060612,
    "win_rate": 0.464980543
  },
  {
    "id": 5144,
    "name": "Cloak and Dagger",
    "img": "https://hgv-hyperstone.azurewebsites.net/abilities/riki_permanent_invisibility.png",
    "is_ultimate": false,
    "has_upgrade": false,
    "picks": 0.0617702454,
    "wins": 0.07575758,
    "win_rate": 0.6097561
  },
  {
    "id": 5242,
    "name": "Diabolic Edict",
    "img": "https://hgv-hyperstone.azurewebsites.net/abilities/leshrac_diabolic_edict.png",
    "is_ultimate": false,
    "has_upgrade": false,
    "picks": 0.121657252,
    "wins": 0.105303027,
    "win_rate": 0.430340558
  },
  {
    "id": 5174,
    "name": "Blink",
    "img": "https://hgv-hyperstone.azurewebsites.net/abilities/queenofpain_blink.png",
    "is_ultimate": false,
    "has_upgrade": false,
    "picks": 0.116760828,
    "wins": 0.12651515,
    "win_rate": 0.5387097
  },
  {
    "id": 5179,
    "name": "Poison Sting",
    "img": "https://hgv-hyperstone.azurewebsites.net/abilities/venomancer_poison_sting.png",
    "is_ultimate": false,
    "has_upgrade": false,
    "picks": 0.345009416,
    "wins": 0.391666681,
    "win_rate": 0.5644105
  },
  {
    "id": 5180,
    "name": "Plague Ward",
    "img": "https://hgv-hyperstone.azurewebsites.net/abilities/venomancer_plague_ward.png",
    "is_ultimate": false,
    "has_upgrade": false,
    "picks": 0.169491529,
    "wins": 0.1621212,
    "win_rate": 0.475555569
  },
  {
    "id": 5471,
    "name": "Illuminate",
    "img": "https://hgv-hyperstone.azurewebsites.net/abilities/keeper_of_the_light_illuminate.png",
    "is_ultimate": false,
    "has_upgrade": false,
    "picks": 0.0244821087,
    "wins": 0.0219696965,
    "win_rate": 0.446153849
  },
  {
    "id": 5632,
    "name": "Gust",
    "img": "https://hgv-hyperstone.azurewebsites.net/abilities/drow_ranger_wave_of_silence.png",
    "is_ultimate": false,
    "has_upgrade": false,
    "picks": 0.304331452,
    "wins": 0.272727281,
    "win_rate": 0.445544541
  },
  {
    "id": 5011,
    "name": "Brain Sap",
    "img": "https://hgv-hyperstone.azurewebsites.net/abilities/bane_brain_sap.png",
    "is_ultimate": false,
    "has_upgrade": true,
    "picks": 0.0779661,
    "wins": 0.07727273,
    "win_rate": 0.492753625
  },
  {
    "id": 5524,
    "name": "Whirling Death",
    "img": "https://hgv-hyperstone.azurewebsites.net/abilities/shredder_whirling_death.png",
    "is_ultimate": false,
    "has_upgrade": false,
    "picks": 0.105084747,
    "wins": 0.09924243,
    "win_rate": 0.469534039
  },
  {
    "id": 5436,
    "name": "Living Armor",
    "img": "https://hgv-hyperstone.azurewebsites.net/abilities/treant_living_armor.png",
    "is_ultimate": false,
    "has_upgrade": false,
    "picks": 0.158192083,
    "wins": 0.1659091,
    "win_rate": 0.5214286
  },
  {
    "id": 5228,
    "name": "Dragon Blood",
    "img": "https://hgv-hyperstone.azurewebsites.net/abilities/dragon_knight_dragon_blood.png",
    "is_ultimate": false,
    "has_upgrade": false,
    "picks": 0.09905838,
    "wins": 0.1030303,
    "win_rate": 0.5171103
  },
  {
    "id": 5115,
    "name": "Slithereen Crush",
    "img": "https://hgv-hyperstone.azurewebsites.net/abilities/slardar_slithereen_crush.png",
    "is_ultimate": false,
    "has_upgrade": false,
    "picks": 0.125800371,
    "wins": 0.137121215,
    "win_rate": 0.5419162
  },
  {
    "id": 5146,
    "name": "Malefice",
    "img": "https://hgv-hyperstone.azurewebsites.net/abilities/enigma_malefice.png",
    "is_ultimate": false,
    "has_upgrade": false,
    "picks": 0.346139371,
    "wins": 0.338636369,
    "win_rate": 0.48639825
  },
  {
    "id": 5434,
    "name": "Nature's Guise",
    "img": "https://hgv-hyperstone.azurewebsites.net/abilities/treant_natures_guise.png",
    "is_ultimate": false,
    "has_upgrade": false,
    "picks": 0.09077213,
    "wins": 0.07727273,
    "win_rate": 0.423236519
  },
  {
    "id": 5525,
    "name": "Timber Chain",
    "img": "https://hgv-hyperstone.azurewebsites.net/abilities/shredder_timber_chain.png",
    "is_ultimate": false,
    "has_upgrade": false,
    "picks": 0.18493408,
    "wins": 0.171212122,
    "win_rate": 0.460285127
  },
  {
    "id": 5464,
    "name": "Spiked Carapace",
    "img": "https://hgv-hyperstone.azurewebsites.net/abilities/nyx_assassin_spiked_carapace.png",
    "is_ultimate": false,
    "has_upgrade": false,
    "picks": 0.180037662,
    "wins": 0.196212128,
    "win_rate": 0.54184103
  },
  {
    "id": 5175,
    "name": "Scream Of Pain",
    "img": "https://hgv-hyperstone.azurewebsites.net/abilities/queenofpain_scream_of_pain.png",
    "is_ultimate": false,
    "has_upgrade": false,
    "picks": 0.140113,
    "wins": 0.12954545,
    "win_rate": 0.459677428
  },
  {
    "id": 5148,
    "name": "Midnight Pulse",
    "img": "https://hgv-hyperstone.azurewebsites.net/abilities/enigma_midnight_pulse.png",
    "is_ultimate": false,
    "has_upgrade": false,
    "picks": 0.09114878,
    "wins": 0.0969696939,
    "win_rate": 0.5289256
  },
  {
    "id": 5637,
    "name": "Fortune's End",
    "img": "https://hgv-hyperstone.azurewebsites.net/abilities/oracle_fortunes_end.png",
    "is_ultimate": false,
    "has_upgrade": false,
    "picks": 0.08323917,
    "wins": 0.07575758,
    "win_rate": 0.4524887
  },
  {
    "id": 5444,
    "name": "Tombstone",
    "img": "https://hgv-hyperstone.azurewebsites.net/abilities/undying_tombstone.png",
    "is_ultimate": false,
    "has_upgrade": false,
    "picks": 0.132203385,
    "wins": 0.131818175,
    "win_rate": 0.4957265
  },
  {
    "id": 5515,
    "name": "Double Edge",
    "img": "https://hgv-hyperstone.azurewebsites.net/abilities/centaur_double_edge.png",
    "is_ultimate": false,
    "has_upgrade": false,
    "picks": 0.09981167,
    "wins": 0.0833333358,
    "win_rate": 0.415094346
  },
  {
    "id": 5247,
    "name": "Nature's Call",
    "img": "https://hgv-hyperstone.azurewebsites.net/abilities/furion_force_of_nature.png",
    "is_ultimate": false,
    "has_upgrade": false,
    "picks": 0.08964218,
    "wins": 0.07878788,
    "win_rate": 0.4369748
  },
  {
    "id": 5653,
    "name": "Cold Embrace",
    "img": "https://hgv-hyperstone.azurewebsites.net/abilities/winter_wyvern_cold_embrace.png",
    "is_ultimate": false,
    "has_upgrade": false,
    "picks": 0.169114873,
    "wins": 0.150757581,
    "win_rate": 0.443207115
  },
  {
    "id": 5102,
    "name": "Burrowstrike",
    "img": "https://hgv-hyperstone.azurewebsites.net/abilities/sandking_burrowstrike.png",
    "is_ultimate": false,
    "has_upgrade": true,
    "picks": 0.0749529153,
    "wins": 0.0780303,
    "win_rate": 0.51758796
  },
  {
    "id": 5605,
    "name": "Flame Guard",
    "img": "https://hgv-hyperstone.azurewebsites.net/abilities/ember_spirit_flame_guard.png",
    "is_ultimate": false,
    "has_upgrade": false,
    "picks": 0.152165726,
    "wins": 0.142424241,
    "win_rate": 0.465346545
  },
  {
    "id": 5353,
    "name": "Charge of Darkness",
    "img": "https://hgv-hyperstone.azurewebsites.net/abilities/spirit_breaker_charge_of_darkness.png",
    "is_ultimate": false,
    "has_upgrade": false,
    "picks": 0.130320147,
    "wins": 0.137121215,
    "win_rate": 0.5231214
  },
  {
    "id": 5604,
    "name": "Sleight of Fist",
    "img": "https://hgv-hyperstone.azurewebsites.net/abilities/ember_spirit_sleight_of_fist.png",
    "is_ultimate": false,
    "has_upgrade": false,
    "picks": 0.203013182,
    "wins": 0.2090909,
    "win_rate": 0.5120594
  },
  {
    "id": 5566,
    "name": "Snowball",
    "img": "https://hgv-hyperstone.azurewebsites.net/abilities/tusk_snowball.png",
    "is_ultimate": false,
    "has_upgrade": false,
    "picks": 0.163841814,
    "wins": 0.1659091,
    "win_rate": 0.503448248
  },
  {
    "id": 5241,
    "name": "Split Earth",
    "img": "https://hgv-hyperstone.azurewebsites.net/abilities/leshrac_split_earth.png",
    "is_ultimate": false,
    "has_upgrade": false,
    "picks": 0.157062143,
    "wins": 0.142424241,
    "win_rate": 0.450839341
  },
  {
    "id": 5025,
    "name": "Aftershock",
    "img": "https://hgv-hyperstone.azurewebsites.net/abilities/earthshaker_aftershock.png",
    "is_ultimate": false,
    "has_upgrade": false,
    "picks": 0.05009416,
    "wins": 0.05757576,
    "win_rate": 0.5714286
  },
  {
    "id": 5223,
    "name": "Moon Glaives",
    "img": "https://hgv-hyperstone.azurewebsites.net/abilities/luna_moon_glaive.png",
    "is_ultimate": false,
    "has_upgrade": false,
    "picks": 0.242184564,
    "wins": 0.275757581,
    "win_rate": 0.5660964
  },
  {
    "id": 5443,
    "name": "Soul Rip",
    "img": "https://hgv-hyperstone.azurewebsites.net/abilities/undying_soul_rip.png",
    "is_ultimate": false,
    "has_upgrade": false,
    "picks": 0.1126177,
    "wins": 0.11212121,
    "win_rate": 0.4949833
  },
  {
    "id": 5139,
    "name": "Voodoo Restoration",
    "img": "https://hgv-hyperstone.azurewebsites.net/abilities/witch_doctor_voodoo_restoration.png",
    "is_ultimate": false,
    "has_upgrade": false,
    "picks": 0.0983050838,
    "wins": 0.0969696939,
    "win_rate": 0.490421444
  },
  {
    "id": 5004,
    "name": "Blink",
    "img": "https://hgv-hyperstone.azurewebsites.net/abilities/antimage_blink.png",
    "is_ultimate": false,
    "has_upgrade": false,
    "picks": 0.145762712,
    "wins": 0.150757581,
    "win_rate": 0.5142119
  },
  {
    "id": 5422,
    "name": "Soul Catcher",
    "img": "https://hgv-hyperstone.azurewebsites.net/abilities/shadow_demon_soul_catcher.png",
    "is_ultimate": false,
    "has_upgrade": false,
    "picks": 0.04858757,
    "wins": 0.0416666679,
    "win_rate": 0.426356584
  },
  {
    "id": 5462,
    "name": "Impale",
    "img": "https://hgv-hyperstone.azurewebsites.net/abilities/nyx_assassin_impale.png",
    "is_ultimate": false,
    "has_upgrade": false,
    "picks": 0.114877589,
    "wins": 0.125,
    "win_rate": 0.5409836
  },
  {
    "id": 5106,
    "name": "Avalanche",
    "img": "https://hgv-hyperstone.azurewebsites.net/abilities/tiny_avalanche.png",
    "is_ultimate": false,
    "has_upgrade": false,
    "picks": 0.0583804138,
    "wins": 0.05757576,
    "win_rate": 0.4903226
  },
  {
    "id": 5276,
    "name": "Crippling Fear",
    "img": "https://hgv-hyperstone.azurewebsites.net/abilities/night_stalker_crippling_fear.png",
    "is_ultimate": false,
    "has_upgrade": false,
    "picks": 0.17062147,
    "wins": 0.172727272,
    "win_rate": 0.5033113
  },
  {
    "id": 5379,
    "name": "Last Word",
    "img": "https://hgv-hyperstone.azurewebsites.net/abilities/silencer_last_word.png",
    "is_ultimate": false,
    "has_upgrade": false,
    "picks": 0.175517887,
    "wins": 0.160606056,
    "win_rate": 0.4549356
  },
  {
    "id": 5162,
    "name": "Fatal Bonds",
    "img": "https://hgv-hyperstone.azurewebsites.net/abilities/warlock_fatal_bonds.png",
    "is_ultimate": false,
    "has_upgrade": false,
    "picks": 0.145009413,
    "wins": 0.139393941,
    "win_rate": 0.477922082
  },
  {
    "id": 5110,
    "name": "Arc Lightning",
    "img": "https://hgv-hyperstone.azurewebsites.net/abilities/zuus_arc_lightning.png",
    "is_ultimate": false,
    "has_upgrade": false,
    "picks": 0.0583804138,
    "wins": 0.05,
    "win_rate": 0.425806463
  },
  {
    "id": 5286,
    "name": "Jinada",
    "img": "https://hgv-hyperstone.azurewebsites.net/abilities/bounty_hunter_jinada.png",
    "is_ultimate": false,
    "has_upgrade": false,
    "picks": 0.24896422,
    "wins": 0.24166666,
    "win_rate": 0.482602119
  },
  {
    "id": 5514,
    "name": "Hoof Stomp",
    "img": "https://hgv-hyperstone.azurewebsites.net/abilities/centaur_hoof_stomp.png",
    "is_ultimate": false,
    "has_upgrade": false,
    "picks": 0.152919024,
    "wins": 0.147727266,
    "win_rate": 0.480295569
  },
  {
    "id": 5438,
    "name": "Fireblast",
    "img": "https://hgv-hyperstone.azurewebsites.net/abilities/ogre_magi_fireblast.png",
    "is_ultimate": false,
    "has_upgrade": false,
    "picks": 0.0975517854,
    "wins": 0.09015152,
    "win_rate": 0.459459454
  },
  {
    "id": 5243,
    "name": "Lightning Storm",
    "img": "https://hgv-hyperstone.azurewebsites.net/abilities/leshrac_lightning_storm.png",
    "is_ultimate": false,
    "has_upgrade": true,
    "picks": 0.0858757049,
    "wins": 0.06515151,
    "win_rate": 0.377192974
  },
  {
    "id": 5340,
    "name": "Scorched Earth",
    "img": "https://hgv-hyperstone.azurewebsites.net/abilities/doom_bringer_scorched_earth.png",
    "is_ultimate": false,
    "has_upgrade": false,
    "picks": 0.08775894,
    "wins": 0.09318182,
    "win_rate": 0.527897
  },
  {
    "id": 5458,
    "name": "Thunder Strike",
    "img": "https://hgv-hyperstone.azurewebsites.net/abilities/disruptor_thunder_strike.png",
    "is_ultimate": false,
    "has_upgrade": false,
    "picks": 0.125047088,
    "wins": 0.0969696939,
    "win_rate": 0.385542154
  },
  {
    "id": 5158,
    "name": "Death Pulse",
    "img": "https://hgv-hyperstone.azurewebsites.net/abilities/necrolyte_death_pulse.png",
    "is_ultimate": false,
    "has_upgrade": false,
    "picks": 0.124293782,
    "wins": 0.12348485,
    "win_rate": 0.4939394
  },
  {
    "id": 5518,
    "name": "Shockwave",
    "img": "https://hgv-hyperstone.azurewebsites.net/abilities/magnataur_shockwave.png",
    "is_ultimate": false,
    "has_upgrade": true,
    "picks": 0.073446326,
    "wins": 0.0704545453,
    "win_rate": 0.476923078
  },
  {
    "id": 5336,
    "name": "Dispersion",
    "img": "https://hgv-hyperstone.azurewebsites.net/abilities/spectre_dispersion.png",
    "is_ultimate": false,
    "has_upgrade": false,
    "picks": 0.152919024,
    "wins": 0.160606056,
    "win_rate": 0.5221675
  },
  {
    "id": 5520,
    "name": "Skewer",
    "img": "https://hgv-hyperstone.azurewebsites.net/abilities/magnataur_skewer.png",
    "is_ultimate": false,
    "has_upgrade": false,
    "picks": 0.1913371,
    "wins": 0.178787872,
    "win_rate": 0.464566916
  },
  {
    "id": 5008,
    "name": "Battle Hunger",
    "img": "https://hgv-hyperstone.azurewebsites.net/abilities/axe_battle_hunger.png",
    "is_ultimate": false,
    "has_upgrade": true,
    "picks": 0.186817333,
    "wins": 0.177272722,
    "win_rate": 0.4717742
  },
  {
    "id": 5679,
    "name": "Spark Wraith",
    "img": "https://hgv-hyperstone.azurewebsites.net/abilities/arc_warden_spark_wraith.png",
    "is_ultimate": false,
    "has_upgrade": false,
    "picks": 0.04708098,
    "wins": 0.03939394,
    "win_rate": 0.416
  },
  {
    "id": 5463,
    "name": "Mana Burn",
    "img": "https://hgv-hyperstone.azurewebsites.net/abilities/nyx_assassin_mana_burn.png",
    "is_ultimate": false,
    "has_upgrade": false,
    "picks": 0.08022599,
    "wins": 0.0734848455,
    "win_rate": 0.455399066
  },
  {
    "id": 5226,
    "name": "Breathe Fire",
    "img": "https://hgv-hyperstone.azurewebsites.net/abilities/dragon_knight_breathe_fire.png",
    "is_ultimate": false,
    "has_upgrade": false,
    "picks": 0.104331449,
    "wins": 0.09621212,
    "win_rate": 0.458483756
  },
  {
    "id": 5239,
    "name": "Rocket Flare",
    "img": "https://hgv-hyperstone.azurewebsites.net/abilities/rattletrap_rocket_flare.png",
    "is_ultimate": false,
    "has_upgrade": false,
    "picks": 0.08813559,
    "wins": 0.0833333358,
    "win_rate": 0.470085472
  },
  {
    "id": 5685,
    "name": "Spirit Siphon",
    "img": "https://hgv-hyperstone.azurewebsites.net/abilities/death_prophet_spirit_siphon.png",
    "is_ultimate": false,
    "has_upgrade": false,
    "picks": 0.13333334,
    "wins": 0.138636366,
    "win_rate": 0.5169492
  },
  {
    "id": 5078,
    "name": "Ether Shock",
    "img": "https://hgv-hyperstone.azurewebsites.net/abilities/shadow_shaman_ether_shock.png",
    "is_ultimate": false,
    "has_upgrade": false,
    "picks": 0.105838038,
    "wins": 0.103787877,
    "win_rate": 0.487544477
  },
  {
    "id": 5098,
    "name": "Static Remnant",
    "img": "https://hgv-hyperstone.azurewebsites.net/abilities/storm_spirit_static_remnant.png",
    "is_ultimate": false,
    "has_upgrade": false,
    "picks": 0.08173258,
    "wins": 0.0621212125,
    "win_rate": 0.3778802
  },
  {
    "id": 5100,
    "name": "Overload",
    "img": "https://hgv-hyperstone.azurewebsites.net/abilities/storm_spirit_overload.png",
    "is_ultimate": false,
    "has_upgrade": false,
    "picks": 0.136346519,
    "wins": 0.108333334,
    "win_rate": 0.395027637
  },
  {
    "id": 6341,
    "name": "Shadow Realm",
    "img": "https://hgv-hyperstone.azurewebsites.net/abilities/dark_willow_shadow_realm.png",
    "is_ultimate": false,
    "has_upgrade": false,
    "picks": 0.1566855,
    "wins": 0.152272731,
    "win_rate": 0.483173072
  },
  {
    "id": 5639,
    "name": "Purifying Flames",
    "img": "https://hgv-hyperstone.azurewebsites.net/abilities/oracle_purifying_flames.png",
    "is_ultimate": false,
    "has_upgrade": true,
    "picks": 0.0779661,
    "wins": 0.06439394,
    "win_rate": 0.410628021
  },
  {
    "id": 5086,
    "name": "Wraithfire Blast",
    "img": "https://hgv-hyperstone.azurewebsites.net/abilities/skeleton_king_hellfire_blast.png",
    "is_ultimate": false,
    "has_upgrade": false,
    "picks": 0.135593221,
    "wins": 0.131818175,
    "win_rate": 0.483333319
  },
  {
    "id": 5071,
    "name": "Waning Rift",
    "img": "https://hgv-hyperstone.azurewebsites.net/abilities/puck_waning_rift.png",
    "is_ultimate": false,
    "has_upgrade": false,
    "picks": 0.0779661,
    "wins": 0.0704545453,
    "win_rate": 0.449275374
  },
  {
    "id": 5118,
    "name": "Gush",
    "img": "https://hgv-hyperstone.azurewebsites.net/abilities/tidehunter_gush.png",
    "is_ultimate": false,
    "has_upgrade": true,
    "picks": 0.10131827,
    "wins": 0.111363634,
    "win_rate": 0.5464684
  },
  {
    "id": 5473,
    "name": "Chakra Magic",
    "img": "https://hgv-hyperstone.azurewebsites.net/abilities/keeper_of_the_light_chakra_magic.png",
    "is_ultimate": false,
    "has_upgrade": false,
    "picks": 0.0282485876,
    "wins": 0.0227272734,
    "win_rate": 0.4
  },
  {
    "id": 5075,
    "name": "Meat Hook",
    "img": "https://hgv-hyperstone.azurewebsites.net/abilities/pudge_meat_hook.png",
    "is_ultimate": false,
    "has_upgrade": true,
    "picks": 0.0549905822,
    "wins": 0.0469696969,
    "win_rate": 0.424657524
  },
  {
    "id": 5329,
    "name": "Test of Faith",
    "img": "https://hgv-hyperstone.azurewebsites.net/abilities/chen_test_of_faith.png",
    "is_ultimate": false,
    "has_upgrade": false,
    "picks": 0.04858757,
    "wins": 0.0416666679,
    "win_rate": 0.426356584
  },
  {
    "id": 5150,
    "name": "Laser",
    "img": "https://hgv-hyperstone.azurewebsites.net/abilities/tinker_laser.png",
    "is_ultimate": false,
    "has_upgrade": true,
    "picks": 0.111111112,
    "wins": 0.102272727,
    "win_rate": 0.457627118
  },
  {
    "id": 5341,
    "name": "Infernal Blade",
    "img": "https://hgv-hyperstone.azurewebsites.net/abilities/doom_bringer_infernal_blade.png",
    "is_ultimate": false,
    "has_upgrade": false,
    "picks": 0.09039548,
    "wins": 0.1,
    "win_rate": 0.55
  },
  {
    "id": 5321,
    "name": "Flamebreak",
    "img": "https://hgv-hyperstone.azurewebsites.net/abilities/batrider_flamebreak.png",
    "is_ultimate": false,
    "has_upgrade": false,
    "picks": 0.0406779647,
    "wins": 0.03409091,
    "win_rate": 0.416666657
  },
  {
    "id": 5147,
    "name": "Demonic Conversion",
    "img": "https://hgv-hyperstone.azurewebsites.net/abilities/enigma_demonic_conversion.png",
    "is_ultimate": false,
    "has_upgrade": false,
    "picks": 0.100941621,
    "wins": 0.09015152,
    "win_rate": 0.444029838
  },
  {
    "id": 5107,
    "name": "Toss",
    "img": "https://hgv-hyperstone.azurewebsites.net/abilities/tiny_toss.png",
    "is_ultimate": false,
    "has_upgrade": false,
    "picks": 0.05762712,
    "wins": 0.05,
    "win_rate": 0.431372553
  },
  {
    "id": 5080,
    "name": "Shackles",
    "img": "https://hgv-hyperstone.azurewebsites.net/abilities/shadow_shaman_shackles.png",
    "is_ultimate": false,
    "has_upgrade": false,
    "picks": 0.0723163858,
    "wins": 0.0598484837,
    "win_rate": 0.411458343
  },
  {
    "id": 5395,
    "name": "Summon Wolves",
    "img": "https://hgv-hyperstone.azurewebsites.net/abilities/lycan_summon_wolves.png",
    "is_ultimate": false,
    "has_upgrade": false,
    "picks": 0.0723163858,
    "wins": 0.05,
    "win_rate": 0.34375
  },
  {
    "id": 5186,
    "name": "Nether Blast",
    "img": "https://hgv-hyperstone.azurewebsites.net/abilities/pugna_nether_blast.png",
    "is_ultimate": false,
    "has_upgrade": false,
    "picks": 0.09416196,
    "wins": 0.07954545,
    "win_rate": 0.42
  },
  {
    "id": 5439,
    "name": "Ignite",
    "img": "https://hgv-hyperstone.azurewebsites.net/abilities/ogre_magi_ignite.png",
    "is_ultimate": false,
    "has_upgrade": false,
    "picks": 0.07608286,
    "wins": 0.0621212125,
    "win_rate": 0.4059406
  },
  {
    "id": 5164,
    "name": "Upheaval",
    "img": "https://hgv-hyperstone.azurewebsites.net/abilities/warlock_upheaval.png",
    "is_ultimate": false,
    "has_upgrade": false,
    "picks": 0.0222222228,
    "wins": 0.01590909,
    "win_rate": 0.3559322
  },
  {
    "id": 5567,
    "name": "Frozen Sigil",
    "img": "https://hgv-hyperstone.azurewebsites.net/abilities/tusk_frozen_sigil.png",
    "is_ultimate": false,
    "has_upgrade": false,
    "picks": 0.03276836,
    "wins": 0.0333333351,
    "win_rate": 0.505747139
  },
  {
    "id": 5187,
    "name": "Decrepify",
    "img": "https://hgv-hyperstone.azurewebsites.net/abilities/pugna_decrepify.png",
    "is_ultimate": false,
    "has_upgrade": false,
    "picks": 0.0320150666,
    "wins": 0.0265151523,
    "win_rate": 0.4117647
  },
  {
    "id": 5046,
    "name": "Mana Drain",
    "img": "https://hgv-hyperstone.azurewebsites.net/abilities/lion_mana_drain.png",
    "is_ultimate": false,
    "has_upgrade": false,
    "picks": 0.05047081,
    "wins": 0.0484848469,
    "win_rate": 0.477611929
  },
  {
    "id": 5152,
    "name": "March of the Machines",
    "img": "https://hgv-hyperstone.azurewebsites.net/abilities/tinker_march_of_the_machines.png",
    "is_ultimate": false,
    "has_upgrade": false,
    "picks": 0.0361581929,
    "wins": 0.0310606062,
    "win_rate": 0.427083343
  },
  {
    "id": 5330,
    "name": "Holy Persuasion",
    "img": "https://hgv-hyperstone.azurewebsites.net/abilities/chen_holy_persuasion.png",
    "is_ultimate": false,
    "has_upgrade": true,
    "picks": 0.0632768348,
    "wins": 0.0522727259,
    "win_rate": 0.4107143
  }
]