[
  {
    "id": 1,
    "name": "Anti-Mage",
    "image_banner": "https://hgv-hyperstone.azurewebsites.net/heroes/banner/npc_dota_hero_antimage.png",
    "image_icon": "https://hgv-hyperstone.azurewebsites.net/heroes/icons/npc_dota_hero_antimage.png",
    "image_profile": "https://hgv-hyperstone.azurewebsites.net/heroes/profile/npc_dota_hero_antimage.png",
    "attribute_primary": "DOTA_ATTRIBUTE_AGILITY",
    "attack_capabilities": "DOTA_UNIT_CAP_MELEE_ATTACK",
    "picks": 0.915422857,
    "wins": 0.8666667,
    "win_rate": 0.494565219
  },
  {
    "id": 2,
    "name": "Axe",
    "image_banner": "https://hgv-hyperstone.azurewebsites.net/heroes/banner/npc_dota_hero_axe.png",
    "image_icon": "https://hgv-hyperstone.azurewebsites.net/heroes/icons/npc_dota_hero_axe.png",
    "image_profile": "https://hgv-hyperstone.azurewebsites.net/heroes/profile/npc_dota_hero_axe.png",
    "attribute_primary": "DOTA_ATTRIBUTE_STRENGTH",
    "attack_capabilities": "DOTA_UNIT_CAP_MELEE_ATTACK",
    "picks": 0.6832504,
    "wins": 0.6730159,
    "win_rate": 0.5145631
  },
  {
    "id": 3,
    "name": "Bane",
    "image_banner": "https://hgv-hyperstone.azurewebsites.net/heroes/banner/npc_dota_hero_bane.png",
    "image_icon": "https://hgv-hyperstone.azurewebsites.net/heroes/icons/npc_dota_hero_bane.png",
    "image_profile": "https://hgv-hyperstone.azurewebsites.net/heroes/profile/npc_dota_hero_bane.png",
    "attribute_primary": "DOTA_ATTRIBUTE_INTELLECT",
    "attack_capabilities": "DOTA_UNIT_CAP_RANGED_ATTACK",
    "picks": 0.711442769,
    "wins": 0.746031761,
    "win_rate": 0.5477855
  },
  {
    "id": 4,
    "name": "Bloodseeker",
    "image_banner": "https://hgv-hyperstone.azurewebsites.net/heroes/banner/npc_dota_hero_bloodseeker.png",
    "image_icon": "https://hgv-hyperstone.azurewebsites.net/heroes/icons/npc_dota_hero_bloodseeker.png",
    "image_profile": "https://hgv-hyperstone.azurewebsites.net/heroes/profile/npc_dota_hero_bloodseeker.png",
    "attribute_primary": "DOTA_ATTRIBUTE_AGILITY",
    "attack_capabilities": "DOTA_UNIT_CAP_MELEE_ATTACK",
    "picks": 0.892205656,
    "wins": 0.8920635,
    "win_rate": 0.522304833
  },
  {
    "id": 5,
    "name": "Crystal Maiden",
    "image_banner": "https://hgv-hyperstone.azurewebsites.net/heroes/banner/npc_dota_hero_crystal_maiden.png",
    "image_icon": "https://hgv-hyperstone.azurewebsites.net/heroes/icons/npc_dota_hero_crystal_maiden.png",
    "image_profile": "https://hgv-hyperstone.azurewebsites.net/heroes/profile/npc_dota_hero_crystal_maiden.png",
    "attribute_primary": "DOTA_ATTRIBUTE_INTELLECT",
    "attack_capabilities": "DOTA_UNIT_CAP_RANGED_ATTACK",
    "picks": 0.5920398,
    "wins": 0.5555556,
    "win_rate": 0.490196079
  },
  {
    "id": 6,
    "name": "Drow Ranger",
    "image_banner": "https://hgv-hyperstone.azurewebsites.net/heroes/banner/npc_dota_hero_drow_ranger.png",
    "image_icon": "https://hgv-hyperstone.azurewebsites.net/heroes/icons/npc_dota_hero_drow_ranger.png",
    "image_profile": "https://hgv-hyperstone.azurewebsites.net/heroes/profile/npc_dota_hero_drow_ranger.png",
    "attribute_primary": "DOTA_ATTRIBUTE_AGILITY",
    "attack_capabilities": "DOTA_UNIT_CAP_RANGED_ATTACK",
    "picks": 0.5339967,
    "wins": 0.507936537,
    "win_rate": 0.496894419
  },
  {
    "id": 7,
    "name": "Earthshaker",
    "image_banner": "https://hgv-hyperstone.azurewebsites.net/heroes/banner/npc_dota_hero_earthshaker.png",
    "image_icon": "https://hgv-hyperstone.azurewebsites.net/heroes/icons/npc_dota_hero_earthshaker.png",
    "image_profile": "https://hgv-hyperstone.azurewebsites.net/heroes/profile/npc_dota_hero_earthshaker.png",
    "attribute_primary": "DOTA_ATTRIBUTE_STRENGTH",
    "attack_capabilities": "DOTA_UNIT_CAP_MELEE_ATTACK",
    "picks": 0.8590381,
    "wins": 0.8095238,
    "win_rate": 0.49227798
  },
  {
    "id": 8,
    "name": "Juggernaut",
    "image_banner": "https://hgv-hyperstone.azurewebsites.net/heroes/banner/npc_dota_hero_juggernaut.png",
    "image_icon": "https://hgv-hyperstone.azurewebsites.net/heroes/icons/npc_dota_hero_juggernaut.png",
    "image_profile": "https://hgv-hyperstone.azurewebsites.net/heroes/profile/npc_dota_hero_juggernaut.png",
    "attribute_primary": "DOTA_ATTRIBUTE_AGILITY",
    "attack_capabilities": "DOTA_UNIT_CAP_MELEE_ATTACK",
    "picks": 0.8391377,
    "wins": 0.7968254,
    "win_rate": 0.496047437
  },
  {
    "id": 9,
    "name": "Mirana",
    "image_banner": "https://hgv-hyperstone.azurewebsites.net/heroes/banner/npc_dota_hero_mirana.png",
    "image_icon": "https://hgv-hyperstone.azurewebsites.net/heroes/icons/npc_dota_hero_mirana.png",
    "image_profile": "https://hgv-hyperstone.azurewebsites.net/heroes/profile/npc_dota_hero_mirana.png",
    "attribute_primary": "DOTA_ATTRIBUTE_AGILITY",
    "attack_capabilities": "DOTA_UNIT_CAP_RANGED_ATTACK",
    "picks": 0.449419558,
    "wins": 0.415873021,
    "win_rate": 0.483394831
  },
  {
    "id": 12,
    "name": "Phantom Lancer",
    "image_banner": "https://hgv-hyperstone.azurewebsites.net/heroes/banner/npc_dota_hero_phantom_lancer.png",
    "image_icon": "https://hgv-hyperstone.azurewebsites.net/heroes/icons/npc_dota_hero_phantom_lancer.png",
    "image_profile": "https://hgv-hyperstone.azurewebsites.net/heroes/profile/npc_dota_hero_phantom_lancer.png",
    "attribute_primary": "DOTA_ATTRIBUTE_AGILITY",
    "attack_capabilities": "DOTA_UNIT_CAP_MELEE_ATTACK",
    "picks": 0.6699834,
    "wins": 0.5904762,
    "win_rate": 0.460396051
  },
  {
    "id": 13,
    "name": "Puck",
    "image_banner": "https://hgv-hyperstone.azurewebsites.net/heroes/banner/npc_dota_hero_puck.png",
    "image_icon": "https://hgv-hyperstone.azurewebsites.net/heroes/icons/npc_dota_hero_puck.png",
    "image_profile": "https://hgv-hyperstone.azurewebsites.net/heroes/profile/npc_dota_hero_puck.png",
    "attribute_primary": "DOTA_ATTRIBUTE_INTELLECT",
    "attack_capabilities": "DOTA_UNIT_CAP_RANGED_ATTACK",
    "picks": 0.411276937,
    "wins": 0.371428579,
    "win_rate": 0.4717742
  },
  {
    "id": 14,
    "name": "Pudge",
    "image_banner": "https://hgv-hyperstone.azurewebsites.net/heroes/banner/npc_dota_hero_pudge.png",
    "image_icon": "https://hgv-hyperstone.azurewebsites.net/heroes/icons/npc_dota_hero_pudge.png",
    "image_profile": "https://hgv-hyperstone.azurewebsites.net/heroes/profile/npc_dota_hero_pudge.png",
    "attribute_primary": "DOTA_ATTRIBUTE_STRENGTH",
    "attack_capabilities": "DOTA_UNIT_CAP_MELEE_ATTACK",
    "picks": 0.7777778,
    "wins": 0.739682555,
    "win_rate": 0.4968017
  },
  {
    "id": 15,
    "name": "Razor",
    "image_banner": "https://hgv-hyperstone.azurewebsites.net/heroes/banner/npc_dota_hero_razor.png",
    "image_icon": "https://hgv-hyperstone.azurewebsites.net/heroes/icons/npc_dota_hero_razor.png",
    "image_profile": "https://hgv-hyperstone.azurewebsites.net/heroes/profile/npc_dota_hero_razor.png",
    "attribute_primary": "DOTA_ATTRIBUTE_AGILITY",
    "attack_capabilities": "DOTA_UNIT_CAP_RANGED_ATTACK",
    "picks": 0.660033166,
    "wins": 0.7111111,
    "win_rate": 0.562814057
  },
  {
    "id": 16,
    "name": "Sand King",
    "image_banner": "https://hgv-hyperstone.azurewebsites.net/heroes/banner/npc_dota_hero_sand_king.png",
    "image_icon": "https://hgv-hyperstone.azurewebsites.net/heroes/icons/npc_dota_hero_sand_king.png",
    "image_profile": "https://hgv-hyperstone.azurewebsites.net/heroes/profile/npc_dota_hero_sand_king.png",
    "attribute_primary": "DOTA_ATTRIBUTE_STRENGTH",
    "attack_capabilities": "DOTA_UNIT_CAP_MELEE_ATTACK",
    "picks": 0.873963535,
    "wins": 0.8730159,
    "win_rate": 0.5218216
  },
  {
    "id": 17,
    "name": "Storm Spirit",
    "image_banner": "https://hgv-hyperstone.azurewebsites.net/heroes/banner/npc_dota_hero_storm_spirit.png",
    "image_icon": "https://hgv-hyperstone.azurewebsites.net/heroes/icons/npc_dota_hero_storm_spirit.png",
    "image_profile": "https://hgv-hyperstone.azurewebsites.net/heroes/profile/npc_dota_hero_storm_spirit.png",
    "attribute_primary": "DOTA_ATTRIBUTE_INTELLECT",
    "attack_capabilities": "DOTA_UNIT_CAP_RANGED_ATTACK",
    "picks": 0.8308458,
    "wins": 0.7587302,
    "win_rate": 0.4770459
  },
  {
    "id": 18,
    "name": "Sven",
    "image_banner": "https://hgv-hyperstone.azurewebsites.net/heroes/banner/npc_dota_hero_sven.png",
    "image_icon": "https://hgv-hyperstone.azurewebsites.net/heroes/icons/npc_dota_hero_sven.png",
    "image_profile": "https://hgv-hyperstone.azurewebsites.net/heroes/profile/npc_dota_hero_sven.png",
    "attribute_primary": "DOTA_ATTRIBUTE_STRENGTH",
    "attack_capabilities": "DOTA_UNIT_CAP_MELEE_ATTACK",
    "picks": 0.9386401,
    "wins": 0.9206349,
    "win_rate": 0.5123675
  },
  {
    "id": 19,
    "name": "Tiny",
    "image_banner": "https://hgv-hyperstone.azurewebsites.net/heroes/banner/npc_dota_hero_tiny.png",
    "image_icon": "https://hgv-hyperstone.azurewebsites.net/heroes/icons/npc_dota_hero_tiny.png",
    "image_profile": "https://hgv-hyperstone.azurewebsites.net/heroes/profile/npc_dota_hero_tiny.png",
    "attribute_primary": "DOTA_ATTRIBUTE_STRENGTH",
    "attack_capabilities": "DOTA_UNIT_CAP_MELEE_ATTACK",
    "picks": 0.424543947,
    "wins": 0.415873021,
    "win_rate": 0.51171875
  },
  {
    "id": 20,
    "name": "Vengeful Spirit",
    "image_banner": "https://hgv-hyperstone.azurewebsites.net/heroes/banner/npc_dota_hero_vengefulspirit.png",
    "image_icon": "https://hgv-hyperstone.azurewebsites.net/heroes/icons/npc_dota_hero_vengefulspirit.png",
    "image_profile": "https://hgv-hyperstone.azurewebsites.net/heroes/profile/npc_dota_hero_vengefulspirit.png",
    "attribute_primary": "DOTA_ATTRIBUTE_AGILITY",
    "attack_capabilities": "DOTA_UNIT_CAP_RANGED_ATTACK",
    "picks": 0.6053068,
    "wins": 0.641269863,
    "win_rate": 0.553424656
  },
  {
    "id": 21,
    "name": "Windranger",
    "image_banner": "https://hgv-hyperstone.azurewebsites.net/heroes/banner/npc_dota_hero_windrunner.png",
    "image_icon": "https://hgv-hyperstone.azurewebsites.net/heroes/icons/npc_dota_hero_windrunner.png",
    "image_profile": "https://hgv-hyperstone.azurewebsites.net/heroes/profile/npc_dota_hero_windrunner.png",
    "attribute_primary": "DOTA_ATTRIBUTE_INTELLECT",
    "attack_capabilities": "DOTA_UNIT_CAP_RANGED_ATTACK",
    "picks": 0.621890545,
    "wins": 0.5587302,
    "win_rate": 0.469333321
  },
  {
    "id": 22,
    "name": "Zeus",
    "image_banner": "https://hgv-hyperstone.azurewebsites.net/heroes/banner/npc_dota_hero_zuus.png",
    "image_icon": "https://hgv-hyperstone.azurewebsites.net/heroes/icons/npc_dota_hero_zuus.png",
    "image_profile": "https://hgv-hyperstone.azurewebsites.net/heroes/profile/npc_dota_hero_zuus.png",
    "attribute_primary": "DOTA_ATTRIBUTE_INTELLECT",
    "attack_capabilities": "DOTA_UNIT_CAP_RANGED_ATTACK",
    "picks": 0.6766169,
    "wins": 0.631746054,
    "win_rate": 0.4877451
  },
  {
    "id": 23,
    "name": "Kunkka",
    "image_banner": "https://hgv-hyperstone.azurewebsites.net/heroes/banner/npc_dota_hero_kunkka.png",
    "image_icon": "https://hgv-hyperstone.azurewebsites.net/heroes/icons/npc_dota_hero_kunkka.png",
    "image_profile": "https://hgv-hyperstone.azurewebsites.net/heroes/profile/npc_dota_hero_kunkka.png",
    "attribute_primary": "DOTA_ATTRIBUTE_STRENGTH",
    "attack_capabilities": "DOTA_UNIT_CAP_MELEE_ATTACK",
    "picks": 0.8391377,
    "wins": 0.9015873,
    "win_rate": 0.5612648
  },
  {
    "id": 25,
    "name": "Lina",
    "image_banner": "https://hgv-hyperstone.azurewebsites.net/heroes/banner/npc_dota_hero_lina.png",
    "image_icon": "https://hgv-hyperstone.azurewebsites.net/heroes/icons/npc_dota_hero_lina.png",
    "image_profile": "https://hgv-hyperstone.azurewebsites.net/heroes/profile/npc_dota_hero_lina.png",
    "attribute_primary": "DOTA_ATTRIBUTE_INTELLECT",
    "attack_capabilities": "DOTA_UNIT_CAP_RANGED_ATTACK",
    "picks": 0.5538972,
    "wins": 0.504761934,
    "win_rate": 0.4760479
  },
  {
    "id": 26,
    "name": "Lion",
    "image_banner": "https://hgv-hyperstone.azurewebsites.net/heroes/banner/npc_dota_hero_lion.png",
    "image_icon": "https://hgv-hyperstone.azurewebsites.net/heroes/icons/npc_dota_hero_lion.png",
    "image_profile": "https://hgv-hyperstone.azurewebsites.net/heroes/profile/npc_dota_hero_lion.png",
    "attribute_primary": "DOTA_ATTRIBUTE_INTELLECT",
    "attack_capabilities": "DOTA_UNIT_CAP_RANGED_ATTACK",
    "picks": 0.8076285,
    "wins": 0.742857158,
    "win_rate": 0.4804928
  },
  {
    "id": 27,
    "name": "Shadow Shaman",
    "image_banner": "https://hgv-hyperstone.azurewebsites.net/heroes/banner/npc_dota_hero_shadow_shaman.png",
    "image_icon": "https://hgv-hyperstone.azurewebsites.net/heroes/icons/npc_dota_hero_shadow_shaman.png",
    "image_profile": "https://hgv-hyperstone.azurewebsites.net/heroes/profile/npc_dota_hero_shadow_shaman.png",
    "attribute_primary": "DOTA_ATTRIBUTE_INTELLECT",
    "attack_capabilities": "DOTA_UNIT_CAP_RANGED_ATTACK",
    "picks": 0.7595357,
    "wins": 0.6920635,
    "win_rate": 0.475982547
  },
  {
    "id": 28,
    "name": "Slardar",
    "image_banner": "https://hgv-hyperstone.azurewebsites.net/heroes/banner/npc_dota_hero_slardar.png",
    "image_icon": "https://hgv-hyperstone.azurewebsites.net/heroes/icons/npc_dota_hero_slardar.png",
    "image_profile": "https://hgv-hyperstone.azurewebsites.net/heroes/profile/npc_dota_hero_slardar.png",
    "attribute_primary": "DOTA_ATTRIBUTE_STRENGTH",
    "attack_capabilities": "DOTA_UNIT_CAP_MELEE_ATTACK",
    "picks": 0.9917081,
    "wins": 0.8920635,
    "win_rate": 0.469899654
  },
  {
    "id": 29,
    "name": "Tidehunter",
    "image_banner": "https://hgv-hyperstone.azurewebsites.net/heroes/banner/npc_dota_hero_tidehunter.png",
    "image_icon": "https://hgv-hyperstone.azurewebsites.net/heroes/icons/npc_dota_hero_tidehunter.png",
    "image_profile": "https://hgv-hyperstone.azurewebsites.net/heroes/profile/npc_dota_hero_tidehunter.png",
    "attribute_primary": "DOTA_ATTRIBUTE_STRENGTH",
    "attack_capabilities": "DOTA_UNIT_CAP_MELEE_ATTACK",
    "picks": 0.7993367,
    "wins": 0.7746032,
    "win_rate": 0.5062241
  },
  {
    "id": 30,
    "name": "Witch Doctor",
    "image_banner": "https://hgv-hyperstone.azurewebsites.net/heroes/banner/npc_dota_hero_witch_doctor.png",
    "image_icon": "https://hgv-hyperstone.azurewebsites.net/heroes/icons/npc_dota_hero_witch_doctor.png",
    "image_profile": "https://hgv-hyperstone.azurewebsites.net/heroes/profile/npc_dota_hero_witch_doctor.png",
    "attribute_primary": "DOTA_ATTRIBUTE_INTELLECT",
    "attack_capabilities": "DOTA_UNIT_CAP_RANGED_ATTACK",
    "picks": 0.7794362,
    "wins": 0.720634937,
    "win_rate": 0.482978731
  },
  {
    "id": 31,
    "name": "Lich",
    "image_banner": "https://hgv-hyperstone.azurewebsites.net/heroes/banner/npc_dota_hero_lich.png",
    "image_icon": "https://hgv-hyperstone.azurewebsites.net/heroes/icons/npc_dota_hero_lich.png",
    "image_profile": "https://hgv-hyperstone.azurewebsites.net/heroes/profile/npc_dota_hero_lich.png",
    "attribute_primary": "DOTA_ATTRIBUTE_INTELLECT",
    "attack_capabilities": "DOTA_UNIT_CAP_RANGED_ATTACK",
    "picks": 0.7247098,
    "wins": 0.7111111,
    "win_rate": 0.5125858
  },
  {
    "id": 32,
    "name": "Riki",
    "image_banner": "https://hgv-hyperstone.azurewebsites.net/heroes/banner/npc_dota_hero_riki.png",
    "image_icon": "https://hgv-hyperstone.azurewebsites.net/heroes/icons/npc_dota_hero_riki.png",
    "image_profile": "https://hgv-hyperstone.azurewebsites.net/heroes/profile/npc_dota_hero_riki.png",
    "attribute_primary": "DOTA_ATTRIBUTE_AGILITY",
    "attack_capabilities": "DOTA_UNIT_CAP_MELEE_ATTACK",
    "picks": 0.955223858,
    "wins": 0.8761905,
    "win_rate": 0.479166657
  },
  {
    "id": 33,
    "name": "Enigma",
    "image_banner": "https://hgv-hyperstone.azurewebsites.net/heroes/banner/npc_dota_hero_enigma.png",
    "image_icon": "https://hgv-hyperstone.azurewebsites.net/heroes/icons/npc_dota_hero_enigma.png",
    "image_profile": "https://hgv-hyperstone.azurewebsites.net/heroes/profile/npc_dota_hero_enigma.png",
    "attribute_primary": "DOTA_ATTRIBUTE_INTELLECT",
    "attack_capabilities": "DOTA_UNIT_CAP_RANGED_ATTACK",
    "picks": 0.719734669,
    "wins": 0.641269863,
    "win_rate": 0.4654378
  },
  {
    "id": 34,
    "name": "Tinker",
    "image_banner": "https://hgv-hyperstone.azurewebsites.net/heroes/banner/npc_dota_hero_tinker.png",
    "image_icon": "https://hgv-hyperstone.azurewebsites.net/heroes/icons/npc_dota_hero_tinker.png",
    "image_profile": "https://hgv-hyperstone.azurewebsites.net/heroes/profile/npc_dota_hero_tinker.png",
    "attribute_primary": "DOTA_ATTRIBUTE_INTELLECT",
    "attack_capabilities": "DOTA_UNIT_CAP_RANGED_ATTACK",
    "picks": 0.7064677,
    "wins": 0.622222245,
    "win_rate": 0.4600939
  },
  {
    "id": 35,
    "name": "Sniper",
    "image_banner": "https://hgv-hyperstone.azurewebsites.net/heroes/banner/npc_dota_hero_sniper.png",
    "image_icon": "https://hgv-hyperstone.azurewebsites.net/heroes/icons/npc_dota_hero_sniper.png",
    "image_profile": "https://hgv-hyperstone.azurewebsites.net/heroes/profile/npc_dota_hero_sniper.png",
    "attribute_primary": "DOTA_ATTRIBUTE_AGILITY",
    "attack_capabilities": "DOTA_UNIT_CAP_RANGED_ATTACK",
    "picks": 0.313432842,
    "wins": 0.317460328,
    "win_rate": 0.529100537
  },
  {
    "id": 36,
    "name": "Necrophos",
    "image_banner": "https://hgv-hyperstone.azurewebsites.net/heroes/banner/npc_dota_hero_necrolyte.png",
    "image_icon": "https://hgv-hyperstone.azurewebsites.net/heroes/icons/npc_dota_hero_necrolyte.png",
    "image_profile": "https://hgv-hyperstone.azurewebsites.net/heroes/profile/npc_dota_hero_necrolyte.png",
    "attribute_primary": "DOTA_ATTRIBUTE_INTELLECT",
    "attack_capabilities": "DOTA_UNIT_CAP_RANGED_ATTACK",
    "picks": 0.6981758,
    "wins": 0.4984127,
    "win_rate": 0.372921616
  },
  {
    "id": 37,
    "name": "Warlock",
    "image_banner": "https://hgv-hyperstone.azurewebsites.net/heroes/banner/npc_dota_hero_warlock.png",
    "image_icon": "https://hgv-hyperstone.azurewebsites.net/heroes/icons/npc_dota_hero_warlock.png",
    "image_profile": "https://hgv-hyperstone.azurewebsites.net/heroes/profile/npc_dota_hero_warlock.png",
    "attribute_primary": "DOTA_ATTRIBUTE_INTELLECT",
    "attack_capabilities": "DOTA_UNIT_CAP_RANGED_ATTACK",
    "picks": 0.8490879,
    "wins": 0.838095248,
    "win_rate": 0.515625
  },
  {
    "id": 39,
    "name": "Queen of Pain",
    "image_banner": "https://hgv-hyperstone.azurewebsites.net/heroes/banner/npc_dota_hero_queenofpain.png",
    "image_icon": "https://hgv-hyperstone.azurewebsites.net/heroes/icons/npc_dota_hero_queenofpain.png",
    "image_profile": "https://hgv-hyperstone.azurewebsites.net/heroes/profile/npc_dota_hero_queenofpain.png",
    "attribute_primary": "DOTA_ATTRIBUTE_INTELLECT",
    "attack_capabilities": "DOTA_UNIT_CAP_RANGED_ATTACK",
    "picks": 0.699834168,
    "wins": 0.6730159,
    "win_rate": 0.502369642
  },
  {
    "id": 40,
    "name": "Venomancer",
    "image_banner": "https://hgv-hyperstone.azurewebsites.net/heroes/banner/npc_dota_hero_venomancer.png",
    "image_icon": "https://hgv-hyperstone.azurewebsites.net/heroes/icons/npc_dota_hero_venomancer.png",
    "image_profile": "https://hgv-hyperstone.azurewebsites.net/heroes/profile/npc_dota_hero_venomancer.png",
    "attribute_primary": "DOTA_ATTRIBUTE_AGILITY",
    "attack_capabilities": "DOTA_UNIT_CAP_RANGED_ATTACK",
    "picks": 0.6766169,
    "wins": 0.5714286,
    "win_rate": 0.441176474
  },
  {
    "id": 41,
    "name": "Faceless Void",
    "image_banner": "https://hgv-hyperstone.azurewebsites.net/heroes/banner/npc_dota_hero_faceless_void.png",
    "image_icon": "https://hgv-hyperstone.azurewebsites.net/heroes/icons/npc_dota_hero_faceless_void.png",
    "image_profile": "https://hgv-hyperstone.azurewebsites.net/heroes/profile/npc_dota_hero_faceless_void.png",
    "attribute_primary": "DOTA_ATTRIBUTE_AGILITY",
    "attack_capabilities": "DOTA_UNIT_CAP_MELEE_ATTACK",
    "picks": 0.7993367,
    "wins": 0.822222233,
    "win_rate": 0.5373444
  },
  {
    "id": 42,
    "name": "Wraith King",
    "image_banner": "https://hgv-hyperstone.azurewebsites.net/heroes/banner/npc_dota_hero_skeleton_king.png",
    "image_icon": "https://hgv-hyperstone.azurewebsites.net/heroes/icons/npc_dota_hero_skeleton_king.png",
    "image_profile": "https://hgv-hyperstone.azurewebsites.net/heroes/profile/npc_dota_hero_skeleton_king.png",
    "attribute_primary": "DOTA_ATTRIBUTE_STRENGTH",
    "attack_capabilities": "DOTA_UNIT_CAP_MELEE_ATTACK",
    "picks": 0.9535655,
    "wins": 0.8793651,
    "win_rate": 0.481739134
  },
  {
    "id": 43,
    "name": "Death Prophet",
    "image_banner": "https://hgv-hyperstone.azurewebsites.net/heroes/banner/npc_dota_hero_death_prophet.png",
    "image_icon": "https://hgv-hyperstone.azurewebsites.net/heroes/icons/npc_dota_hero_death_prophet.png",
    "image_profile": "https://hgv-hyperstone.azurewebsites.net/heroes/profile/npc_dota_hero_death_prophet.png",
    "attribute_primary": "DOTA_ATTRIBUTE_INTELLECT",
    "attack_capabilities": "DOTA_UNIT_CAP_RANGED_ATTACK",
    "picks": 0.708126,
    "wins": 0.730158746,
    "win_rate": 0.5386417
  },
  {
    "id": 44,
    "name": "Phantom Assassin",
    "image_banner": "https://hgv-hyperstone.azurewebsites.net/heroes/banner/npc_dota_hero_phantom_assassin.png",
    "image_icon": "https://hgv-hyperstone.azurewebsites.net/heroes/icons/npc_dota_hero_phantom_assassin.png",
    "image_profile": "https://hgv-hyperstone.azurewebsites.net/heroes/profile/npc_dota_hero_phantom_assassin.png",
    "attribute_primary": "DOTA_ATTRIBUTE_AGILITY",
    "attack_capabilities": "DOTA_UNIT_CAP_MELEE_ATTACK",
    "picks": 0.7280265,
    "wins": 0.644444466,
    "win_rate": 0.4624146
  },
  {
    "id": 45,
    "name": "Pugna",
    "image_banner": "https://hgv-hyperstone.azurewebsites.net/heroes/banner/npc_dota_hero_pugna.png",
    "image_icon": "https://hgv-hyperstone.azurewebsites.net/heroes/icons/npc_dota_hero_pugna.png",
    "image_profile": "https://hgv-hyperstone.azurewebsites.net/heroes/profile/npc_dota_hero_pugna.png",
    "attribute_primary": "DOTA_ATTRIBUTE_INTELLECT",
    "attack_capabilities": "DOTA_UNIT_CAP_RANGED_ATTACK",
    "picks": 0.708126,
    "wins": 0.6666667,
    "win_rate": 0.4918033
  },
  {
    "id": 46,
    "name": "Templar Assassin",
    "image_banner": "https://hgv-hyperstone.azurewebsites.net/heroes/banner/npc_dota_hero_templar_assassin.png",
    "image_icon": "https://hgv-hyperstone.azurewebsites.net/heroes/icons/npc_dota_hero_templar_assassin.png",
    "image_profile": "https://hgv-hyperstone.azurewebsites.net/heroes/profile/npc_dota_hero_templar_assassin.png",
    "attribute_primary": "DOTA_ATTRIBUTE_AGILITY",
    "attack_capabilities": "DOTA_UNIT_CAP_RANGED_ATTACK",
    "picks": 0.7578773,
    "wins": 0.7015873,
    "win_rate": 0.483588636
  },
  {
    "id": 47,
    "name": "Viper",
    "image_banner": "https://hgv-hyperstone.azurewebsites.net/heroes/banner/npc_dota_hero_viper.png",
    "image_icon": "https://hgv-hyperstone.azurewebsites.net/heroes/icons/npc_dota_hero_viper.png",
    "image_profile": "https://hgv-hyperstone.azurewebsites.net/heroes/profile/npc_dota_hero_viper.png",
    "attribute_primary": "DOTA_ATTRIBUTE_AGILITY",
    "attack_capabilities": "DOTA_UNIT_CAP_RANGED_ATTACK",
    "picks": 0.5854063,
    "wins": 0.517460346,
    "win_rate": 0.461756378
  },
  {
    "id": 48,
    "name": "Luna",
    "image_banner": "https://hgv-hyperstone.azurewebsites.net/heroes/banner/npc_dota_hero_luna.png",
    "image_icon": "https://hgv-hyperstone.azurewebsites.net/heroes/icons/npc_dota_hero_luna.png",
    "image_profile": "https://hgv-hyperstone.azurewebsites.net/heroes/profile/npc_dota_hero_luna.png",
    "attribute_primary": "DOTA_ATTRIBUTE_AGILITY",
    "attack_capabilities": "DOTA_UNIT_CAP_RANGED_ATTACK",
    "picks": 0.313432842,
    "wins": 0.339682549,
    "win_rate": 0.566137552
  },
  {
    "id": 49,
    "name": "Dragon Knight",
    "image_banner": "https://hgv-hyperstone.azurewebsites.net/heroes/banner/npc_dota_hero_dragon_knight.png",
    "image_icon": "https://hgv-hyperstone.azurewebsites.net/heroes/icons/npc_dota_hero_dragon_knight.png",
    "image_profile": "https://hgv-hyperstone.azurewebsites.net/heroes/profile/npc_dota_hero_dragon_knight.png",
    "attribute_primary": "DOTA_ATTRIBUTE_STRENGTH",
    "attack_capabilities": "DOTA_UNIT_CAP_MELEE_ATTACK",
    "picks": 0.49751243,
    "wins": 0.479365081,
    "win_rate": 0.50333333
  },
  {
    "id": 50,
    "name": "Dazzle",
    "image_banner": "https://hgv-hyperstone.azurewebsites.net/heroes/banner/npc_dota_hero_dazzle.png",
    "image_icon": "https://hgv-hyperstone.azurewebsites.net/heroes/icons/npc_dota_hero_dazzle.png",
    "image_profile": "https://hgv-hyperstone.azurewebsites.net/heroes/profile/npc_dota_hero_dazzle.png",
    "attribute_primary": "DOTA_ATTRIBUTE_INTELLECT",
    "attack_capabilities": "DOTA_UNIT_CAP_RANGED_ATTACK",
    "picks": 0.6749585,
    "wins": 0.6539683,
    "win_rate": 0.5061425
  },
  {
    "id": 51,
    "name": "Clockwerk",
    "image_banner": "https://hgv-hyperstone.azurewebsites.net/heroes/banner/npc_dota_hero_rattletrap.png",
    "image_icon": "https://hgv-hyperstone.azurewebsites.net/heroes/icons/npc_dota_hero_rattletrap.png",
    "image_profile": "https://hgv-hyperstone.azurewebsites.net/heroes/profile/npc_dota_hero_rattletrap.png",
    "attribute_primary": "DOTA_ATTRIBUTE_STRENGTH",
    "attack_capabilities": "DOTA_UNIT_CAP_MELEE_ATTACK",
    "picks": 0.7595357,
    "wins": 0.7587302,
    "win_rate": 0.5218341
  },
  {
    "id": 52,
    "name": "Leshrac",
    "image_banner": "https://hgv-hyperstone.azurewebsites.net/heroes/banner/npc_dota_hero_leshrac.png",
    "image_icon": "https://hgv-hyperstone.azurewebsites.net/heroes/icons/npc_dota_hero_leshrac.png",
    "image_profile": "https://hgv-hyperstone.azurewebsites.net/heroes/profile/npc_dota_hero_leshrac.png",
    "attribute_primary": "DOTA_ATTRIBUTE_INTELLECT",
    "attack_capabilities": "DOTA_UNIT_CAP_RANGED_ATTACK",
    "picks": 0.772802651,
    "wins": 0.7111111,
    "win_rate": 0.4806867
  },
  {
    "id": 53,
    "name": "Nature's Prophet",
    "image_banner": "https://hgv-hyperstone.azurewebsites.net/heroes/banner/npc_dota_hero_furion.png",
    "image_icon": "https://hgv-hyperstone.azurewebsites.net/heroes/icons/npc_dota_hero_furion.png",
    "image_profile": "https://hgv-hyperstone.azurewebsites.net/heroes/profile/npc_dota_hero_furion.png",
    "attribute_primary": "DOTA_ATTRIBUTE_INTELLECT",
    "attack_capabilities": "DOTA_UNIT_CAP_RANGED_ATTACK",
    "picks": 0.615257,
    "wins": 0.6507937,
    "win_rate": 0.5525606
  },
  {
    "id": 54,
    "name": "Lifestealer",
    "image_banner": "https://hgv-hyperstone.azurewebsites.net/heroes/banner/npc_dota_hero_life_stealer.png",
    "image_icon": "https://hgv-hyperstone.azurewebsites.net/heroes/icons/npc_dota_hero_life_stealer.png",
    "image_profile": "https://hgv-hyperstone.azurewebsites.net/heroes/profile/npc_dota_hero_life_stealer.png",
    "attribute_primary": "DOTA_ATTRIBUTE_STRENGTH",
    "attack_capabilities": "DOTA_UNIT_CAP_MELEE_ATTACK",
    "picks": 0.4809287,
    "wins": 0.4920635,
    "win_rate": 0.5344828
  },
  {
    "id": 55,
    "name": "Dark Seer",
    "image_banner": "https://hgv-hyperstone.azurewebsites.net/heroes/banner/npc_dota_hero_dark_seer.png",
    "image_icon": "https://hgv-hyperstone.azurewebsites.net/heroes/icons/npc_dota_hero_dark_seer.png",
    "image_profile": "https://hgv-hyperstone.azurewebsites.net/heroes/profile/npc_dota_hero_dark_seer.png",
    "attribute_primary": "DOTA_ATTRIBUTE_INTELLECT",
    "attack_capabilities": "DOTA_UNIT_CAP_MELEE_ATTACK",
    "picks": 0.8374793,
    "wins": 0.736507952,
    "win_rate": 0.459405929
  },
  {
    "id": 56,
    "name": "Clinkz",
    "image_banner": "https://hgv-hyperstone.azurewebsites.net/heroes/banner/npc_dota_hero_clinkz.png",
    "image_icon": "https://hgv-hyperstone.azurewebsites.net/heroes/icons/npc_dota_hero_clinkz.png",
    "image_profile": "https://hgv-hyperstone.azurewebsites.net/heroes/profile/npc_dota_hero_clinkz.png",
    "attribute_primary": "DOTA_ATTRIBUTE_AGILITY",
    "attack_capabilities": "DOTA_UNIT_CAP_RANGED_ATTACK",
    "picks": 0.6583748,
    "wins": 0.5936508,
    "win_rate": 0.471032739
  },
  {
    "id": 57,
    "name": "Omniknight",
    "image_banner": "https://hgv-hyperstone.azurewebsites.net/heroes/banner/npc_dota_hero_omniknight.png",
    "image_icon": "https://hgv-hyperstone.azurewebsites.net/heroes/icons/npc_dota_hero_omniknight.png",
    "image_profile": "https://hgv-hyperstone.azurewebsites.net/heroes/profile/npc_dota_hero_omniknight.png",
    "attribute_primary": "DOTA_ATTRIBUTE_STRENGTH",
    "attack_capabilities": "DOTA_UNIT_CAP_MELEE_ATTACK",
    "picks": 0.812603652,
    "wins": 0.75555557,
    "win_rate": 0.4857143
  },
  {
    "id": 58,
    "name": "Enchantress",
    "image_banner": "https://hgv-hyperstone.azurewebsites.net/heroes/banner/npc_dota_hero_enchantress.png",
    "image_icon": "https://hgv-hyperstone.azurewebsites.net/heroes/icons/npc_dota_hero_enchantress.png",
    "image_profile": "https://hgv-hyperstone.azurewebsites.net/heroes/profile/npc_dota_hero_enchantress.png",
    "attribute_primary": "DOTA_ATTRIBUTE_INTELLECT",
    "attack_capabilities": "DOTA_UNIT_CAP_RANGED_ATTACK",
    "picks": 0.6749585,
    "wins": 0.619047642,
    "win_rate": 0.4791155
  },
  {
    "id": 59,
    "name": "Huskar",
    "image_banner": "https://hgv-hyperstone.azurewebsites.net/heroes/banner/npc_dota_hero_huskar.png",
    "image_icon": "https://hgv-hyperstone.azurewebsites.net/heroes/icons/npc_dota_hero_huskar.png",
    "image_profile": "https://hgv-hyperstone.azurewebsites.net/heroes/profile/npc_dota_hero_huskar.png",
    "attribute_primary": "DOTA_ATTRIBUTE_STRENGTH",
    "attack_capabilities": "DOTA_UNIT_CAP_RANGED_ATTACK",
    "picks": 0.713101149,
    "wins": 0.6888889,
    "win_rate": 0.5046512
  },
  {
    "id": 60,
    "name": "Night Stalker",
    "image_banner": "https://hgv-hyperstone.azurewebsites.net/heroes/banner/npc_dota_hero_night_stalker.png",
    "image_icon": "https://hgv-hyperstone.azurewebsites.net/heroes/icons/npc_dota_hero_night_stalker.png",
    "image_profile": "https://hgv-hyperstone.azurewebsites.net/heroes/profile/npc_dota_hero_night_stalker.png",
    "attribute_primary": "DOTA_ATTRIBUTE_STRENGTH",
    "attack_capabilities": "DOTA_UNIT_CAP_MELEE_ATTACK",
    "picks": 0.864013255,
    "wins": 0.9142857,
    "win_rate": 0.552783132
  },
  {
    "id": 61,
    "name": "Broodmother",
    "image_banner": "https://hgv-hyperstone.azurewebsites.net/heroes/banner/npc_dota_hero_broodmother.png",
    "image_icon": "https://hgv-hyperstone.azurewebsites.net/heroes/icons/npc_dota_hero_broodmother.png",
    "image_profile": "https://hgv-hyperstone.azurewebsites.net/heroes/profile/npc_dota_hero_broodmother.png",
    "attribute_primary": "DOTA_ATTRIBUTE_AGILITY",
    "attack_capabilities": "DOTA_UNIT_CAP_MELEE_ATTACK",
    "picks": 0.932006657,
    "wins": 0.7777778,
    "win_rate": 0.435943067
  },
  {
    "id": 62,
    "name": "Bounty Hunter",
    "image_banner": "https://hgv-hyperstone.azurewebsites.net/heroes/banner/npc_dota_hero_bounty_hunter.png",
    "image_icon": "https://hgv-hyperstone.azurewebsites.net/heroes/icons/npc_dota_hero_bounty_hunter.png",
    "image_profile": "https://hgv-hyperstone.azurewebsites.net/heroes/profile/npc_dota_hero_bounty_hunter.png",
    "attribute_primary": "DOTA_ATTRIBUTE_AGILITY",
    "attack_capabilities": "DOTA_UNIT_CAP_MELEE_ATTACK",
    "picks": 0.865671635,
    "wins": 0.815873,
    "win_rate": 0.492337167
  },
  {
    "id": 63,
    "name": "Weaver",
    "image_banner": "https://hgv-hyperstone.azurewebsites.net/heroes/banner/npc_dota_hero_weaver.png",
    "image_icon": "https://hgv-hyperstone.azurewebsites.net/heroes/icons/npc_dota_hero_weaver.png",
    "image_profile": "https://hgv-hyperstone.azurewebsites.net/heroes/profile/npc_dota_hero_weaver.png",
    "attribute_primary": "DOTA_ATTRIBUTE_AGILITY",
    "attack_capabilities": "DOTA_UNIT_CAP_RANGED_ATTACK",
    "picks": 0.73963517,
    "wins": 0.631746054,
    "win_rate": 0.446188331
  },
  {
    "id": 64,
    "name": "Jakiro",
    "image_banner": "https://hgv-hyperstone.azurewebsites.net/heroes/banner/npc_dota_hero_jakiro.png",
    "image_icon": "https://hgv-hyperstone.azurewebsites.net/heroes/icons/npc_dota_hero_jakiro.png",
    "image_profile": "https://hgv-hyperstone.azurewebsites.net/heroes/profile/npc_dota_hero_jakiro.png",
    "attribute_primary": "DOTA_ATTRIBUTE_INTELLECT",
    "attack_capabilities": "DOTA_UNIT_CAP_RANGED_ATTACK",
    "picks": 0.633499146,
    "wins": 0.5936508,
    "win_rate": 0.4895288
  },
  {
    "id": 65,
    "name": "Batrider",
    "image_banner": "https://hgv-hyperstone.azurewebsites.net/heroes/banner/npc_dota_hero_batrider.png",
    "image_icon": "https://hgv-hyperstone.azurewebsites.net/heroes/icons/npc_dota_hero_batrider.png",
    "image_profile": "https://hgv-hyperstone.azurewebsites.net/heroes/profile/npc_dota_hero_batrider.png",
    "attribute_primary": "DOTA_ATTRIBUTE_INTELLECT",
    "attack_capabilities": "DOTA_UNIT_CAP_RANGED_ATTACK",
    "picks": 0.8822554,
    "wins": 0.7968254,
    "win_rate": 0.4718045
  },
  {
    "id": 66,
    "name": "Chen",
    "image_banner": "https://hgv-hyperstone.azurewebsites.net/heroes/banner/npc_dota_hero_chen.png",
    "image_icon": "https://hgv-hyperstone.azurewebsites.net/heroes/icons/npc_dota_hero_chen.png",
    "image_profile": "https://hgv-hyperstone.azurewebsites.net/heroes/profile/npc_dota_hero_chen.png",
    "attribute_primary": "DOTA_ATTRIBUTE_INTELLECT",
    "attack_capabilities": "DOTA_UNIT_CAP_RANGED_ATTACK",
    "picks": 0.8358209,
    "wins": 0.8095238,
    "win_rate": 0.505952358
  },
  {
    "id": 67,
    "name": "Spectre",
    "image_banner": "https://hgv-hyperstone.azurewebsites.net/heroes/banner/npc_dota_hero_spectre.png",
    "image_icon": "https://hgv-hyperstone.azurewebsites.net/heroes/icons/npc_dota_hero_spectre.png",
    "image_profile": "https://hgv-hyperstone.azurewebsites.net/heroes/profile/npc_dota_hero_spectre.png",
    "attribute_primary": "DOTA_ATTRIBUTE_AGILITY",
    "attack_capabilities": "DOTA_UNIT_CAP_MELEE_ATTACK",
    "picks": 0.590381444,
    "wins": 0.4952381,
    "win_rate": 0.438202262
  },
  {
    "id": 68,
    "name": "Ancient Apparition",
    "image_banner": "https://hgv-hyperstone.azurewebsites.net/heroes/banner/npc_dota_hero_ancient_apparition.png",
    "image_icon": "https://hgv-hyperstone.azurewebsites.net/heroes/icons/npc_dota_hero_ancient_apparition.png",
    "image_profile": "https://hgv-hyperstone.azurewebsites.net/heroes/profile/npc_dota_hero_ancient_apparition.png",
    "attribute_primary": "DOTA_ATTRIBUTE_INTELLECT",
    "attack_capabilities": "DOTA_UNIT_CAP_RANGED_ATTACK",
    "picks": 0.8789386,
    "wins": 0.7936508,
    "win_rate": 0.4716981
  },
  {
    "id": 69,
    "name": "Doom",
    "image_banner": "https://hgv-hyperstone.azurewebsites.net/heroes/banner/npc_dota_hero_doom_bringer.png",
    "image_icon": "https://hgv-hyperstone.azurewebsites.net/heroes/icons/npc_dota_hero_doom_bringer.png",
    "image_profile": "https://hgv-hyperstone.azurewebsites.net/heroes/profile/npc_dota_hero_doom_bringer.png",
    "attribute_primary": "DOTA_ATTRIBUTE_STRENGTH",
    "attack_capabilities": "DOTA_UNIT_CAP_MELEE_ATTACK",
    "picks": 0.517412961,
    "wins": 0.4952381,
    "win_rate": 0.5
  },
  {
    "id": 70,
    "name": "Ursa",
    "image_banner": "https://hgv-hyperstone.azurewebsites.net/heroes/banner/npc_dota_hero_ursa.png",
    "image_icon": "https://hgv-hyperstone.azurewebsites.net/heroes/icons/npc_dota_hero_ursa.png",
    "image_profile": "https://hgv-hyperstone.azurewebsites.net/heroes/profile/npc_dota_hero_ursa.png",
    "attribute_primary": "DOTA_ATTRIBUTE_AGILITY",
    "attack_capabilities": "DOTA_UNIT_CAP_MELEE_ATTACK",
    "picks": 0.9270315,
    "wins": 0.9079365,
    "win_rate": 0.5116279
  },
  {
    "id": 71,
    "name": "Spirit Breaker",
    "image_banner": "https://hgv-hyperstone.azurewebsites.net/heroes/banner/npc_dota_hero_spirit_breaker.png",
    "image_icon": "https://hgv-hyperstone.azurewebsites.net/heroes/icons/npc_dota_hero_spirit_breaker.png",
    "image_profile": "https://hgv-hyperstone.azurewebsites.net/heroes/profile/npc_dota_hero_spirit_breaker.png",
    "attribute_primary": "DOTA_ATTRIBUTE_STRENGTH",
    "attack_capabilities": "DOTA_UNIT_CAP_MELEE_ATTACK",
    "picks": 1.0,
    "wins": 0.965079367,
    "win_rate": 0.5041459
  },
  {
    "id": 72,
    "name": "Gyrocopter",
    "image_banner": "https://hgv-hyperstone.azurewebsites.net/heroes/banner/npc_dota_hero_gyrocopter.png",
    "image_icon": "https://hgv-hyperstone.azurewebsites.net/heroes/icons/npc_dota_hero_gyrocopter.png",
    "image_profile": "https://hgv-hyperstone.azurewebsites.net/heroes/profile/npc_dota_hero_gyrocopter.png",
    "attribute_primary": "DOTA_ATTRIBUTE_AGILITY",
    "attack_capabilities": "DOTA_UNIT_CAP_RANGED_ATTACK",
    "picks": 0.51077944,
    "wins": 0.5555556,
    "win_rate": 0.5681818
  },
  {
    "id": 75,
    "name": "Silencer",
    "image_banner": "https://hgv-hyperstone.azurewebsites.net/heroes/banner/npc_dota_hero_silencer.png",
    "image_icon": "https://hgv-hyperstone.azurewebsites.net/heroes/icons/npc_dota_hero_silencer.png",
    "image_profile": "https://hgv-hyperstone.azurewebsites.net/heroes/profile/npc_dota_hero_silencer.png",
    "attribute_primary": "DOTA_ATTRIBUTE_INTELLECT",
    "attack_capabilities": "DOTA_UNIT_CAP_RANGED_ATTACK",
    "picks": 0.5854063,
    "wins": 0.6603175,
    "win_rate": 0.5892351
  },
  {
    "id": 76,
    "name": "Outworld Devourer",
    "image_banner": "https://hgv-hyperstone.azurewebsites.net/heroes/banner/npc_dota_hero_obsidian_destroyer.png",
    "image_icon": "https://hgv-hyperstone.azurewebsites.net/heroes/icons/npc_dota_hero_obsidian_destroyer.png",
    "image_profile": "https://hgv-hyperstone.azurewebsites.net/heroes/profile/npc_dota_hero_obsidian_destroyer.png",
    "attribute_primary": "DOTA_ATTRIBUTE_INTELLECT",
    "attack_capabilities": "DOTA_UNIT_CAP_RANGED_ATTACK",
    "picks": 0.5837479,
    "wins": 0.568254,
    "win_rate": 0.508522749
  },
  {
    "id": 77,
    "name": "Lycan",
    "image_banner": "https://hgv-hyperstone.azurewebsites.net/heroes/banner/npc_dota_hero_lycan.png",
    "image_icon": "https://hgv-hyperstone.azurewebsites.net/heroes/icons/npc_dota_hero_lycan.png",
    "image_profile": "https://hgv-hyperstone.azurewebsites.net/heroes/profile/npc_dota_hero_lycan.png",
    "attribute_primary": "DOTA_ATTRIBUTE_STRENGTH",
    "attack_capabilities": "DOTA_UNIT_CAP_MELEE_ATTACK",
    "picks": 0.9004975,
    "wins": 0.8825397,
    "win_rate": 0.5119705
  },
  {
    "id": 78,
    "name": "Brewmaster",
    "image_banner": "https://hgv-hyperstone.azurewebsites.net/heroes/banner/npc_dota_hero_brewmaster.png",
    "image_icon": "https://hgv-hyperstone.azurewebsites.net/heroes/icons/npc_dota_hero_brewmaster.png",
    "image_profile": "https://hgv-hyperstone.azurewebsites.net/heroes/profile/npc_dota_hero_brewmaster.png",
    "attribute_primary": "DOTA_ATTRIBUTE_STRENGTH",
    "attack_capabilities": "DOTA_UNIT_CAP_MELEE_ATTACK",
    "picks": 0.812603652,
    "wins": 0.7777778,
    "win_rate": 0.5
  },
  {
    "id": 79,
    "name": "Shadow Demon",
    "image_banner": "https://hgv-hyperstone.azurewebsites.net/heroes/banner/npc_dota_hero_shadow_demon.png",
    "image_icon": "https://hgv-hyperstone.azurewebsites.net/heroes/icons/npc_dota_hero_shadow_demon.png",
    "image_profile": "https://hgv-hyperstone.azurewebsites.net/heroes/profile/npc_dota_hero_shadow_demon.png",
    "attribute_primary": "DOTA_ATTRIBUTE_INTELLECT",
    "attack_capabilities": "DOTA_UNIT_CAP_RANGED_ATTACK",
    "picks": 0.530679941,
    "wins": 0.526984155,
    "win_rate": 0.51875
  },
  {
    "id": 81,
    "name": "Chaos Knight",
    "image_banner": "https://hgv-hyperstone.azurewebsites.net/heroes/banner/npc_dota_hero_chaos_knight.png",
    "image_icon": "https://hgv-hyperstone.azurewebsites.net/heroes/icons/npc_dota_hero_chaos_knight.png",
    "image_profile": "https://hgv-hyperstone.azurewebsites.net/heroes/profile/npc_dota_hero_chaos_knight.png",
    "attribute_primary": "DOTA_ATTRIBUTE_STRENGTH",
    "attack_capabilities": "DOTA_UNIT_CAP_MELEE_ATTACK",
    "picks": 0.8374793,
    "wins": 0.841269851,
    "win_rate": 0.5247525
  },
  {
    "id": 83,
    "name": "Treant Protector",
    "image_banner": "https://hgv-hyperstone.azurewebsites.net/heroes/banner/npc_dota_hero_treant.png",
    "image_icon": "https://hgv-hyperstone.azurewebsites.net/heroes/icons/npc_dota_hero_treant.png",
    "image_profile": "https://hgv-hyperstone.azurewebsites.net/heroes/profile/npc_dota_hero_treant.png",
    "attribute_primary": "DOTA_ATTRIBUTE_STRENGTH",
    "attack_capabilities": "DOTA_UNIT_CAP_MELEE_ATTACK",
    "picks": 0.936981738,
    "wins": 0.85079366,
    "win_rate": 0.4743363
  },
  {
    "id": 84,
    "name": "Ogre Magi",
    "image_banner": "https://hgv-hyperstone.azurewebsites.net/heroes/banner/npc_dota_hero_ogre_magi.png",
    "image_icon": "https://hgv-hyperstone.azurewebsites.net/heroes/icons/npc_dota_hero_ogre_magi.png",
    "image_profile": "https://hgv-hyperstone.azurewebsites.net/heroes/profile/npc_dota_hero_ogre_magi.png",
    "attribute_primary": "DOTA_ATTRIBUTE_INTELLECT",
    "attack_capabilities": "DOTA_UNIT_CAP_MELEE_ATTACK",
    "picks": 0.50912106,
    "wins": 0.5587302,
    "win_rate": 0.573289931
  },
  {
    "id": 85,
    "name": "Undying",
    "image_banner": "https://hgv-hyperstone.azurewebsites.net/heroes/banner/npc_dota_hero_undying.png",
    "image_icon": "https://hgv-hyperstone.azurewebsites.net/heroes/icons/npc_dota_hero_undying.png",
    "image_profile": "https://hgv-hyperstone.azurewebsites.net/heroes/profile/npc_dota_hero_undying.png",
    "attribute_primary": "DOTA_ATTRIBUTE_STRENGTH",
    "attack_capabilities": "DOTA_UNIT_CAP_MELEE_ATTACK",
    "picks": 0.814262033,
    "wins": 0.784127,
    "win_rate": 0.503055
  },
  {
    "id": 87,
    "name": "Disruptor",
    "image_banner": "https://hgv-hyperstone.azurewebsites.net/heroes/banner/npc_dota_hero_disruptor.png",
    "image_icon": "https://hgv-hyperstone.azurewebsites.net/heroes/icons/npc_dota_hero_disruptor.png",
    "image_profile": "https://hgv-hyperstone.azurewebsites.net/heroes/profile/npc_dota_hero_disruptor.png",
    "attribute_primary": "DOTA_ATTRIBUTE_INTELLECT",
    "attack_capabilities": "DOTA_UNIT_CAP_RANGED_ATTACK",
    "picks": 0.840796,
    "wins": 0.752380967,
    "win_rate": 0.467455626
  },
  {
    "id": 88,
    "name": "Nyx Assassin",
    "image_banner": "https://hgv-hyperstone.azurewebsites.net/heroes/banner/npc_dota_hero_nyx_assassin.png",
    "image_icon": "https://hgv-hyperstone.azurewebsites.net/heroes/icons/npc_dota_hero_nyx_assassin.png",
    "image_profile": "https://hgv-hyperstone.azurewebsites.net/heroes/profile/npc_dota_hero_nyx_assassin.png",
    "attribute_primary": "DOTA_ATTRIBUTE_AGILITY",
    "attack_capabilities": "DOTA_UNIT_CAP_MELEE_ATTACK",
    "picks": 0.804311752,
    "wins": 0.7079365,
    "win_rate": 0.4597938
  },
  {
    "id": 89,
    "name": "Naga Siren",
    "image_banner": "https://hgv-hyperstone.azurewebsites.net/heroes/banner/npc_dota_hero_naga_siren.png",
    "image_icon": "https://hgv-hyperstone.azurewebsites.net/heroes/icons/npc_dota_hero_naga_siren.png",
    "image_profile": "https://hgv-hyperstone.azurewebsites.net/heroes/profile/npc_dota_hero_naga_siren.png",
    "attribute_primary": "DOTA_ATTRIBUTE_AGILITY",
    "attack_capabilities": "DOTA_UNIT_CAP_MELEE_ATTACK",
    "picks": 0.673300147,
    "wins": 0.7079365,
    "win_rate": 0.5492611
  },
  {
    "id": 90,
    "name": "Keeper of the Light",
    "image_banner": "https://hgv-hyperstone.azurewebsites.net/heroes/banner/npc_dota_hero_keeper_of_the_light.png",
    "image_icon": "https://hgv-hyperstone.azurewebsites.net/heroes/icons/npc_dota_hero_keeper_of_the_light.png",
    "image_profile": "https://hgv-hyperstone.azurewebsites.net/heroes/profile/npc_dota_hero_keeper_of_the_light.png",
    "attribute_primary": "DOTA_ATTRIBUTE_INTELLECT",
    "attack_capabilities": "DOTA_UNIT_CAP_RANGED_ATTACK",
    "picks": 0.5190713,
    "wins": 0.526984155,
    "win_rate": 0.53035146
  },
  {
    "id": 92,
    "name": "Visage",
    "image_banner": "https://hgv-hyperstone.azurewebsites.net/heroes/banner/npc_dota_hero_visage.png",
    "image_icon": "https://hgv-hyperstone.azurewebsites.net/heroes/icons/npc_dota_hero_visage.png",
    "image_profile": "https://hgv-hyperstone.azurewebsites.net/heroes/profile/npc_dota_hero_visage.png",
    "attribute_primary": "DOTA_ATTRIBUTE_INTELLECT",
    "attack_capabilities": "DOTA_UNIT_CAP_RANGED_ATTACK",
    "picks": 0.8308458,
    "wins": 0.7047619,
    "win_rate": 0.443113774
  },
  {
    "id": 93,
    "name": "Slark",
    "image_banner": "https://hgv-hyperstone.azurewebsites.net/heroes/banner/npc_dota_hero_slark.png",
    "image_icon": "https://hgv-hyperstone.azurewebsites.net/heroes/icons/npc_dota_hero_slark.png",
    "image_profile": "https://hgv-hyperstone.azurewebsites.net/heroes/profile/npc_dota_hero_slark.png",
    "attribute_primary": "DOTA_ATTRIBUTE_AGILITY",
    "attack_capabilities": "DOTA_UNIT_CAP_MELEE_ATTACK",
    "picks": 0.885572135,
    "wins": 0.746031761,
    "win_rate": 0.440074921
  },
  {
    "id": 94,
    "name": "Medusa",
    "image_banner": "https://hgv-hyperstone.azurewebsites.net/heroes/banner/npc_dota_hero_medusa.png",
    "image_icon": "https://hgv-hyperstone.azurewebsites.net/heroes/icons/npc_dota_hero_medusa.png",
    "image_profile": "https://hgv-hyperstone.azurewebsites.net/heroes/profile/npc_dota_hero_medusa.png",
    "attribute_primary": "DOTA_ATTRIBUTE_AGILITY",
    "attack_capabilities": "DOTA_UNIT_CAP_RANGED_ATTACK",
    "picks": 0.412935317,
    "wins": 0.3809524,
    "win_rate": 0.481927723
  },
  {
    "id": 95,
    "name": "Troll Warlord",
    "image_banner": "https://hgv-hyperstone.azurewebsites.net/heroes/banner/npc_dota_hero_troll_warlord.png",
    "image_icon": "https://hgv-hyperstone.azurewebsites.net/heroes/icons/npc_dota_hero_troll_warlord.png",
    "image_profile": "https://hgv-hyperstone.azurewebsites.net/heroes/profile/npc_dota_hero_troll_warlord.png",
    "attribute_primary": "DOTA_ATTRIBUTE_AGILITY",
    "attack_capabilities": "DOTA_UNIT_CAP_RANGED_ATTACK",
    "picks": 0.550580442,
    "wins": 0.530158758,
    "win_rate": 0.503012061
  },
  {
    "id": 96,
    "name": "Centaur Warrunner",
    "image_banner": "https://hgv-hyperstone.azurewebsites.net/heroes/banner/npc_dota_hero_centaur.png",
    "image_icon": "https://hgv-hyperstone.azurewebsites.net/heroes/icons/npc_dota_hero_centaur.png",
    "image_profile": "https://hgv-hyperstone.azurewebsites.net/heroes/profile/npc_dota_hero_centaur.png",
    "attribute_primary": "DOTA_ATTRIBUTE_STRENGTH",
    "attack_capabilities": "DOTA_UNIT_CAP_MELEE_ATTACK",
    "picks": 0.668325067,
    "wins": 0.7015873,
    "win_rate": 0.5483871
  },
  {
    "id": 97,
    "name": "Magnus",
    "image_banner": "https://hgv-hyperstone.azurewebsites.net/heroes/banner/npc_dota_hero_magnataur.png",
    "image_icon": "https://hgv-hyperstone.azurewebsites.net/heroes/icons/npc_dota_hero_magnataur.png",
    "image_profile": "https://hgv-hyperstone.azurewebsites.net/heroes/profile/npc_dota_hero_magnataur.png",
    "attribute_primary": "DOTA_ATTRIBUTE_STRENGTH",
    "attack_capabilities": "DOTA_UNIT_CAP_MELEE_ATTACK",
    "picks": 0.923714757,
    "wins": 1.0,
    "win_rate": 0.565529644
  },
  {
    "id": 98,
    "name": "Timbersaw",
    "image_banner": "https://hgv-hyperstone.azurewebsites.net/heroes/banner/npc_dota_hero_shredder.png",
    "image_icon": "https://hgv-hyperstone.azurewebsites.net/heroes/icons/npc_dota_hero_shredder.png",
    "image_profile": "https://hgv-hyperstone.azurewebsites.net/heroes/profile/npc_dota_hero_shredder.png",
    "attribute_primary": "DOTA_ATTRIBUTE_STRENGTH",
    "attack_capabilities": "DOTA_UNIT_CAP_MELEE_ATTACK",
    "picks": 0.75290215,
    "wins": 0.628571451,
    "win_rate": 0.436123341
  },
  {
    "id": 99,
    "name": "Bristleback",
    "image_banner": "https://hgv-hyperstone.azurewebsites.net/heroes/banner/npc_dota_hero_bristleback.png",
    "image_icon": "https://hgv-hyperstone.azurewebsites.net/heroes/icons/npc_dota_hero_bristleback.png",
    "image_profile": "https://hgv-hyperstone.azurewebsites.net/heroes/profile/npc_dota_hero_bristleback.png",
    "attribute_primary": "DOTA_ATTRIBUTE_STRENGTH",
    "attack_capabilities": "DOTA_UNIT_CAP_MELEE_ATTACK",
    "picks": 0.76285243,
    "wins": 0.7714286,
    "win_rate": 0.5282609
  },
  {
    "id": 100,
    "name": "Tusk",
    "image_banner": "https://hgv-hyperstone.azurewebsites.net/heroes/banner/npc_dota_hero_tusk.png",
    "image_icon": "https://hgv-hyperstone.azurewebsites.net/heroes/icons/npc_dota_hero_tusk.png",
    "image_profile": "https://hgv-hyperstone.azurewebsites.net/heroes/profile/npc_dota_hero_tusk.png",
    "attribute_primary": "DOTA_ATTRIBUTE_STRENGTH",
    "attack_capabilities": "DOTA_UNIT_CAP_MELEE_ATTACK",
    "picks": 0.897180736,
    "wins": 0.85079366,
    "win_rate": 0.495378941
  },
  {
    "id": 101,
    "name": "Skywrath Mage",
    "image_banner": "https://hgv-hyperstone.azurewebsites.net/heroes/banner/npc_dota_hero_skywrath_mage.png",
    "image_icon": "https://hgv-hyperstone.azurewebsites.net/heroes/icons/npc_dota_hero_skywrath_mage.png",
    "image_profile": "https://hgv-hyperstone.azurewebsites.net/heroes/profile/npc_dota_hero_skywrath_mage.png",
    "attribute_primary": "DOTA_ATTRIBUTE_INTELLECT",
    "attack_capabilities": "DOTA_UNIT_CAP_RANGED_ATTACK",
    "picks": 0.7993367,
    "wins": 0.7714286,
    "win_rate": 0.5041494
  },
  {
    "id": 102,
    "name": "Abaddon",
    "image_banner": "https://hgv-hyperstone.azurewebsites.net/heroes/banner/npc_dota_hero_abaddon.png",
    "image_icon": "https://hgv-hyperstone.azurewebsites.net/heroes/icons/npc_dota_hero_abaddon.png",
    "image_profile": "https://hgv-hyperstone.azurewebsites.net/heroes/profile/npc_dota_hero_abaddon.png",
    "attribute_primary": "DOTA_ATTRIBUTE_STRENGTH",
    "attack_capabilities": "DOTA_UNIT_CAP_MELEE_ATTACK",
    "picks": 0.8756219,
    "wins": 0.847619057,
    "win_rate": 0.5056818
  },
  {
    "id": 103,
    "name": "Elder Titan",
    "image_banner": "https://hgv-hyperstone.azurewebsites.net/heroes/banner/npc_dota_hero_elder_titan.png",
    "image_icon": "https://hgv-hyperstone.azurewebsites.net/heroes/icons/npc_dota_hero_elder_titan.png",
    "image_profile": "https://hgv-hyperstone.azurewebsites.net/heroes/profile/npc_dota_hero_elder_titan.png",
    "attribute_primary": "DOTA_ATTRIBUTE_STRENGTH",
    "attack_capabilities": "DOTA_UNIT_CAP_MELEE_ATTACK",
    "picks": 0.5588723,
    "wins": 0.533333361,
    "win_rate": 0.498516321
  },
  {
    "id": 104,
    "name": "Legion Commander",
    "image_banner": "https://hgv-hyperstone.azurewebsites.net/heroes/banner/npc_dota_hero_legion_commander.png",
    "image_icon": "https://hgv-hyperstone.azurewebsites.net/heroes/icons/npc_dota_hero_legion_commander.png",
    "image_profile": "https://hgv-hyperstone.azurewebsites.net/heroes/profile/npc_dota_hero_legion_commander.png",
    "attribute_primary": "DOTA_ATTRIBUTE_STRENGTH",
    "attack_capabilities": "DOTA_UNIT_CAP_MELEE_ATTACK",
    "picks": 0.8772803,
    "wins": 0.834920645,
    "win_rate": 0.497164458
  },
  {
    "id": 106,
    "name": "Ember Spirit",
    "image_banner": "https://hgv-hyperstone.azurewebsites.net/heroes/banner/npc_dota_hero_ember_spirit.png",
    "image_icon": "https://hgv-hyperstone.azurewebsites.net/heroes/icons/npc_dota_hero_ember_spirit.png",
    "image_profile": "https://hgv-hyperstone.azurewebsites.net/heroes/profile/npc_dota_hero_ember_spirit.png",
    "attribute_primary": "DOTA_ATTRIBUTE_AGILITY",
    "attack_capabilities": "DOTA_UNIT_CAP_MELEE_ATTACK",
    "picks": 0.7280265,
    "wins": 0.6857143,
    "win_rate": 0.492027342
  },
  {
    "id": 108,
    "name": "Underlord",
    "image_banner": "https://hgv-hyperstone.azurewebsites.net/heroes/banner/npc_dota_hero_abyssal_underlord.png",
    "image_icon": "https://hgv-hyperstone.azurewebsites.net/heroes/icons/npc_dota_hero_abyssal_underlord.png",
    "image_profile": "https://hgv-hyperstone.azurewebsites.net/heroes/profile/npc_dota_hero_abyssal_underlord.png",
    "attribute_primary": "DOTA_ATTRIBUTE_STRENGTH",
    "attack_capabilities": "DOTA_UNIT_CAP_MELEE_ATTACK",
    "picks": 0.7893864,
    "wins": 0.7873016,
    "win_rate": 0.521008432
  },
  {
    "id": 109,
    "name": "Terrorblade",
    "image_banner": "https://hgv-hyperstone.azurewebsites.net/heroes/banner/npc_dota_hero_terrorblade.png",
    "image_icon": "https://hgv-hyperstone.azurewebsites.net/heroes/icons/npc_dota_hero_terrorblade.png",
    "image_profile": "https://hgv-hyperstone.azurewebsites.net/heroes/profile/npc_dota_hero_terrorblade.png",
    "attribute_primary": "DOTA_ATTRIBUTE_AGILITY",
    "attack_capabilities": "DOTA_UNIT_CAP_MELEE_ATTACK",
    "picks": 0.444444448,
    "wins": 0.450793654,
    "win_rate": 0.5298507
  },
  {
    "id": 110,
    "name": "Phoenix",
    "image_banner": "https://hgv-hyperstone.azurewebsites.net/heroes/banner/npc_dota_hero_phoenix.png",
    "image_icon": "https://hgv-hyperstone.azurewebsites.net/heroes/icons/npc_dota_hero_phoenix.png",
    "image_profile": "https://hgv-hyperstone.azurewebsites.net/heroes/profile/npc_dota_hero_phoenix.png",
    "attribute_primary": "DOTA_ATTRIBUTE_STRENGTH",
    "attack_capabilities": "DOTA_UNIT_CAP_RANGED_ATTACK",
    "picks": 0.5058043,
    "wins": 0.5460318,
    "win_rate": 0.563934445
  },
  {
    "id": 111,
    "name": "Oracle",
    "image_banner": "https://hgv-hyperstone.azurewebsites.net/heroes/banner/npc_dota_hero_oracle.png",
    "image_icon": "https://hgv-hyperstone.azurewebsites.net/heroes/icons/npc_dota_hero_oracle.png",
    "image_profile": "https://hgv-hyperstone.azurewebsites.net/heroes/profile/npc_dota_hero_oracle.png",
    "attribute_primary": "DOTA_ATTRIBUTE_INTELLECT",
    "attack_capabilities": "DOTA_UNIT_CAP_RANGED_ATTACK",
    "picks": 0.8590381,
    "wins": 0.844444454,
    "win_rate": 0.5135135
  },
  {
    "id": 112,
    "name": "Winter Wyvern",
    "image_banner": "https://hgv-hyperstone.azurewebsites.net/heroes/banner/npc_dota_hero_winter_wyvern.png",
    "image_icon": "https://hgv-hyperstone.azurewebsites.net/heroes/icons/npc_dota_hero_winter_wyvern.png",
    "image_profile": "https://hgv-hyperstone.azurewebsites.net/heroes/profile/npc_dota_hero_winter_wyvern.png",
    "attribute_primary": "DOTA_ATTRIBUTE_INTELLECT",
    "attack_capabilities": "DOTA_UNIT_CAP_RANGED_ATTACK",
    "picks": 0.7296849,
    "wins": 0.6507937,
    "win_rate": 0.4659091
  },
  {
    "id": 113,
    "name": "Arc Warden",
    "image_banner": "https://hgv-hyperstone.azurewebsites.net/heroes/banner/npc_dota_hero_arc_warden.png",
    "image_icon": "https://hgv-hyperstone.azurewebsites.net/heroes/icons/npc_dota_hero_arc_warden.png",
    "image_profile": "https://hgv-hyperstone.azurewebsites.net/heroes/profile/npc_dota_hero_arc_warden.png",
    "attribute_primary": "DOTA_ATTRIBUTE_AGILITY",
    "attack_capabilities": "DOTA_UNIT_CAP_RANGED_ATTACK",
    "picks": 0.379767835,
    "wins": 0.3968254,
    "win_rate": 0.5458515
  },
  {
    "id": 119,
    "name": "Dark Willow",
    "image_banner": "https://hgv-hyperstone.azurewebsites.net/heroes/banner/npc_dota_hero_dark_willow.png",
    "image_icon": "https://hgv-hyperstone.azurewebsites.net/heroes/icons/npc_dota_hero_dark_willow.png",
    "image_profile": "https://hgv-hyperstone.azurewebsites.net/heroes/profile/npc_dota_hero_dark_willow.png",
    "attribute_primary": "DOTA_ATTRIBUTE_INTELLECT",
    "attack_capabilities": "DOTA_UNIT_CAP_RANGED_ATTACK",
    "picks": 0.462686568,
    "wins": 0.412698418,
    "win_rate": 0.465949833
  },
  {
    "id": 120,
    "name": "Pangolier",
    "image_banner": "https://hgv-hyperstone.azurewebsites.net/heroes/banner/npc_dota_hero_pangolier.png",
    "image_icon": "https://hgv-hyperstone.azurewebsites.net/heroes/icons/npc_dota_hero_pangolier.png",
    "image_profile": "https://hgv-hyperstone.azurewebsites.net/heroes/profile/npc_dota_hero_pangolier.png",
    "attribute_primary": "DOTA_ATTRIBUTE_AGILITY",
    "attack_capabilities": "DOTA_UNIT_CAP_MELEE_ATTACK",
    "picks": 0.8424544,
    "wins": 0.7746032,
    "win_rate": 0.48031497
  },
  {
    "id": 121,
    "name": "Grimstroke",
    "image_banner": "https://hgv-hyperstone.azurewebsites.net/heroes/banner/npc_dota_hero_grimstroke.png",
    "image_icon": "https://hgv-hyperstone.azurewebsites.net/heroes/icons/npc_dota_hero_grimstroke.png",
    "image_profile": "https://hgv-hyperstone.azurewebsites.net/heroes/profile/npc_dota_hero_grimstroke.png",
    "attribute_primary": "DOTA_ATTRIBUTE_INTELLECT",
    "attack_capabilities": "DOTA_UNIT_CAP_RANGED_ATTACK",
    "picks": 0.805970132,
    "wins": 0.749206364,
    "win_rate": 0.485596716
  }
]